Workbook

Sheet 00_Read_Me
A1: APEXCART RETAIL INC. — ANALYTICS WORKBOOK
A2: Synthetic portfolio data. Read the scope notes before interpreting sample worksheets.
A4: Worksheet | B4: Scope and interpretation
A5: 01_Raw_Data | B5: A sample of up to 1,500 raw order-detail rows joined to their raw order/customer fields.
A6: 02_Data_Cleaning | B6: Formula demonstrations over 500 sample rows; this is not the production cleaning pipeline.
A7: 03_Customers | B7: The first 1,000 cleaned customer records.
A8: 04_Products | B8: The cleaned 500-product catalog.
A9: 05_Orders | B9: The first 2,000 cleaned order-detail rows with workbook formulas.
A10: 06_Pivot_Analysis | B10: Formula analysis of the sample in 05_Orders, not full-warehouse totals.
A11: 07_KPI_Summary | B11: Formula examples only; official targets are not assumed.
A12: 08_Business_Insights | B12: Current full-warehouse findings, computed from the SQLite database.
A13: 09_Warehouse_KPIs | B13: Static SQL-calculated totals and record counts for the full current warehouse.
A16: Cleaning pipeline | B16: scripts/clean_raw_datasets.py is the reproducible raw-to-clean pipeline. Unlike the illustrative formulas above, it rejects orders with missing customer keys and records transformations in data/cleaned/cleaning_audit.json.
A18: Financial scope | B18: SQL line-item sales and profit include all stored order statuses, including cancelled orders. Refund-adjusted profit subtracts recorded refunds only; it is not operating profit or EBITDA. Formula cells are calculated by Excel when the workbook is opened.

Sheet 01_Raw_Data
A1: APEXCART RETAIL INC. — RAW TRANSACTION INGESTION FEED
A2: Uncleaned source transactions containing real-world anomalies: date format variances, whitespace, negative quantities, text discount %, and missing keys.
A4: Order_ID | B4: Order_Date_Raw | C4: Customer_ID_Raw | D4: Customer_Name_Raw | E4: Product_ID | F4: Quantity_Raw | G4: Unit_Price | H4: Discount_Raw | I4: Shipping_Mode_Raw | J4: Sales_Channel | K4: Region_Raw
A5: ORD-000001 | B5: 2025-03-14 | C5: CUST-03473 | D5: Samuel Evans | E5: PRD-0308 | F5: 1 | G5: 61.03 | H5: 0.05 | I5: Standard Ground | J5: Mobile App | K5: REG-LATAM
A6: ORD-000002 | B6: 2023-09-25 | C6: CUST-03511 | D6: Karen Gray | E6: PRD-0203 | F6: 3 | G6: 991.36 | H6: 0.05 | I6: Standard Ground | J6: Mobile App | K6: REG-APAC
A7: ORD-000003 | B7: 2025-08-03 | C7: CUST-00043 | D7: Heather Hughes | E7: PRD-0360 | F7: 2 | G7: 465.92 | H7: 0.0 | I7: Express Air | J7: B2B Portal | K7: REG-NA
A8: ORD-000003 | B8: 2025-08-03 | C8: CUST-00043 | D8: Heather Hughes | E8: PRD-0429 | F8: 1 | G8: 790.21 | H8: 0.1 | I8: Express Air | J8: B2B Portal | K8: REG-NA
A9: ORD-000003 | B9: 2025-08-03 | C9: CUST-00043 | D9: Heather Hughes | E9: PRD-0166 | F9: 2 | G9: 173.5 | H9: 0.1 | I9: Express Air | J9: B2B Portal | K9: REG-NA
A10: ORD-000003 | B10: 2025-08-03 | C10: CUST-00043 | D10: Heather Hughes | E10: PRD-0317 | F10: 1 | G10: 484.56 | H10: 0.0 | I10: Express Air | J10: B2B Portal | K10: REG-NA
A11: ORD-000003 | B11: 2025-08-03 | C11: CUST-00043 | D11: Heather Hughes | E11: PRD-0249 | F11: 1 | G11: 69.32 | H11: 0.1 | I11: Express Air | J11: B2B Portal | K11: REG-NA
A12: ORD-000004 | B12: 2025-03-04 | C12: CUST-03363 | D12: Carolyn King | E12: PRD-0141 | F12: 3 | G12: 53.7 | H12: 0.0 | I12: Standard Ground | J12: Direct Web | K12: REG-APAC
A13: ORD-000004 | B13: 2025-03-04 | C13: CUST-03363 | D13: Carolyn King | E13: PRD-0388 | F13: 1 | G13: 318.52 | H13: 0.0 | I13: Standard Ground | J13: Direct Web | K13: REG-APAC
A14: ORD-000004 | B14: 2025-03-04 | C14: CUST-03363 | D14: Carolyn King | E14: PRD-0301 | F14: 1 | G14: 528.29 | H14: 0.15 | I14: Standard Ground | J14: Direct Web | K14: REG-APAC
A15: ORD-000004 | B15: 2025-03-04 | C15: CUST-03363 | D15: Carolyn King | E15: PRD-0399 | F15: 2 | G15: 933.08 | H15: 0.05 | I15: Standard Ground | J15: Direct Web | K15: REG-APAC
A16: ORD-000005 | B16: 2023-09-26 | C16: CUST-01966 | D16: Helen Bennett | E16: PRD-0248 | F16: 2 | G16: 603.58 | H16: 0.05 | I16: Standard Ground | J16: Direct Web | K16: REG-NA
... A35: ORD-000013 | B35: 2023-08-10 | C35: CUST-03549 | D35: Stephen Gray | E35: PRD-0415 | F35: 1 | G35: 934.21 | H35: 0.0 | I35: Standard Ground | J35: Direct Web | K35: REG-APAC
A36: ORD-000014 | B36: 2025-04-25 | E36: PRD-0215 | F36: 1 | G36: 1006.33 | H36: 0.0 | I36: Standard Ground | J36: Direct Web
A37: ORD-000015 | B37: 2024-09-16 | C37: CUST-05715 | D37: Jerry Kim | E37: PRD-0108 | F37: 1 | G37: 217.9 | H37: 0.1 | I37: Freight | J37: Direct Web | K37: REG-NA
A38: ORD-000015 | B38: 2024-09-16 | C38: CUST-05715 | D38: Jerry Kim | E38: PRD-0191 | F38: 1 | G38: 45.09 | H38: 0.0 | I38: Freight | J38: Direct Web | K38: REG-NA
A39: ORD-000016 | B39: 2023-08-12 | C39: CUST-03436 | D39: Betty Sanders | E39: PRD-0026 | F39: 1 | G39: 469.49 | H39: 0.0 | I39: Standard Ground | J39: Direct Web | K39: REG-EU
A40: ORD-000017 | B40: 2025-02-19 | C40: CUST-05569 | D40: Benjamin Morris | E40: PRD-0094 | F40: 1 | G40: 282.3 | H40: 0.1 | I40: Same-Day Priority | J40: Mobile App | K40: REG-NA
A41: ORD-000018 | B41: 2023-11-05 | C41: CUST-01039 | D41: Sarah Lewis | E41: PRD-0254 | F41: 3 | G41: 219.63 | H41: 0.0 | I41: Standard Ground | J41: Direct Web | K41: REG-NA
A42: ORD-000019 | B42: 2024-11-10 | C42: CUST-01504 | D42: Samantha Miller | E42: PRD-0417 | F42: 1 | G42: 134.04 | H42: 0.3 | I42: Express Air | J42: Direct Web | K42: REG-NA
A43: ORD-000019 | B43: 2024-11-10 | C43: CUST-01504 | D43: Samantha Miller | E43: PRD-0163 | F43: 3 | G43: 101.4 | H43: 0.0 | I43: Express Air | J43: Direct Web | K43: REG-NA
A44: ORD-000019 | B44: 2024-11-10 | C44: CUST-01504 | D44: Samantha Miller | E44: PRD-0154 | F44: 3 | G44: 168.94 | H44: 0.0 | I44: Express Air | J44: Direct Web | K44: REG-NA
A45: ORD-000020 | B45: 03/18/2024 | C45: CUST-07544 | D45: Jonathan Patel | E45: PRD-0184 | F45: 1 | G45: 79.57 | H45: 0.3 | I45: Standard Ground | J45: Mobile App | K45: REG-EU
A46: ORD-000021 | B46: 2024-10-17 | C46: CUST-00428 | D46: Gregory Rogers | E46: PRD-0336 | F46: 3 | G46: 216.76 | H46: 10% | I46: Express Air | J46: B2B Portal | K46: REG-APAC
A47: ORD-000022 | B47: 2025-03-29 | C47: CUST-05119 | D47: Sharon Gomez | E47: PRD-0131 | F47: 1 | G47: 66.07 | H47: 0.1 | I47: Standard Ground | J47: Direct Web | K47: REG-APAC
A48: ORD-000023 | B48: 2025-02-12 | C48: CUST-06053 | D48: Nicole Bennett | E48: PRD-0342 | F48: 1 | G48: 994.42 | H48: 0.0 | I48: Freight | J48: Mobile App | K48: REG-NA
... A166: ORD-000081 | B166: 2024-03-28 | C166: CUST-01064 | D166: Jack Turner | E166: PRD-0285 | F166: 1 | G166: 269.59 | H166: 0.3 | I166: Standard Ground | J166: Affiliate Partner | K166: REG-EU
A167: ORD-000082 | B167: 2023-11-07 | E167: PRD-0344 | F167: 2 | G167: 337.02 | H167: 0.05 | I167: Standard Ground | J167: Mobile App
A168: ORD-000083 | B168: 2023-12-12 | C168: CUST-03910 | D168: Catherine White | E168: PRD-0133 | F168: 3 | G168: 673.35 | H168: 0.2 | I168: Express Air | J168: Direct Web | K168: REG-LATAM
A169: ORD-000083 | B169: 2023-12-12 | C169: CUST-03910 | D169: Catherine White | E169: PRD-0240 | F169: 1 | G169: 656.01 | H169: 0.05 | I169: Express Air | J169: Direct Web | K169: REG-LATAM
A170: ORD-000084 | B170: 2024-09-05 | C170: CUST-00136 | D170: Maria Garcia | E170: PRD-0119 | F170: 8 | G170: 11.35 | H170: 0.0 | I170: Express Air | J170: Direct Web | K170: REG-NA
A171: ORD-000085 | B171: 01-09-2024 | C171: CUST-05314 | D171: Nicholas Stewart | E171: PRD-0003 | F171: 1 | G171: 807.39 | H171: 0.05 | I171: Standard Ground | J171: Direct Web | K171: REG-LATAM
A172: ORD-000085 | B172: 01-09-2024 | C172: CUST-05314 | D172: Nicholas Stewart | E172: PRD-0348 | F172: 4 | G172: 792.82 | H172: 0.1 | I172: Standard Ground | J172: Direct Web | K172: REG-LATAM
A173: ORD-000085 | B173: 01-09-2024 | C173: CUST-05314 | D173: Nicholas Stewart | E173: PRD-0459 | F173: 2 | G173: 55.95 | H173: 0.05 | I173: Standard Ground | J173: Direct Web | K173: REG-LATAM
A174: ORD-000085 | B174: 01-09-2024 | C174: CUST-05314 | D174: Nicholas Stewart | E174: PRD-0037 | F174: 1 | G174: 499.93 | H174: 0.0 | I174: Standard Ground | J174: Direct Web | K174: REG-LATAM
A175: ORD-000086 | B175: 2025-03-24 | C175: CUST-01200 | D175: Mark Wright | E175: PRD-0034 | F175: 1 | G175: 52.58 | H175: 0.05 | I175: Standard Ground | J175: Mobile App | K175: REG-EU
A176: ORD-000086 | B176: 2025-03-24 | C176: CUST-01200 | D176: Mark Wright | E176: PRD-0308 | F176: 1 | G176: 61.03 | H176: 0.0 | I176: Standard Ground | J176: Mobile App | K176: REG-EU
A177: ORD-000086 | B177: 2025-03-24 | C177: CUST-01200 | D177: Mark Wright | E177: PRD-0311 | F177: 1 | G177: 7.85 | H177: 0.1 | I177: Standard Ground | J177: Mobile App | K177: REG-EU
A178: ORD-000087 | B178: 2024-03-24 | C178: CUST-07052 | D178: Paul Sanders | E178: PRD-0063 | F178: 1 | G178: 62.68 | H178: 0.05 | I178: Same-Day Priority | J178: Direct Web | K178: REG-NA
A179: ORD-000087 | B179: 2024-03-24 | C179: CUST-07052 | D179: Paul Sanders | E179: PRD-0266 | F179: 4 | G179: 170.34 | H179: 0.05 | I179: Same-Day Priority | J179: Direct Web | K179: REG-NA
... A194: ORD-000090 | B194: 2025-11-20 | C194: CUST-05381 | D194: Jessica Price | E194: PRD-0253 | F194: 1 | G194: 514.94 | H194: 0.0 | I194: Express Air | J194: Direct Web | K194: REG-APAC
A195: ORD-000091 | B195: 2023-11-05 | E195: PRD-0446 | F195: 1 | G195: 610.12 | H195: 0.05 | I195: Express Air | J195: Direct Web
A196: ORD-000092 | B196: 2024-03-11 | C196: CUST-07450 | D196: Sarah Peterson | E196: PRD-0204 | F196: 2 | G196: 46.46 | H196: 0.15 | I196: Standard Ground | J196: Mobile App | K196: REG-NA
A197: ORD-000092 | B197: 2024-03-11 | C197: CUST-07450 | D197: Sarah Peterson | E197: PRD-0005 | F197: 1 | G197: 148.59 | H197: 0.05 | I197: Standard Ground | J197: Mobile App | K197: REG-NA
A198: ORD-000093 | B198: 2024-06-24 | C198: CUST-06221 | D198: Sarah Richardson | E198: PRD-0389 | F198: 3 | G198: 355.7 | H198: 0.3 | I198: Standard Ground | J198: B2B Portal | K198: REG-NA
A199: ORD-000093 | B199: 2024-06-24 | C199: CUST-06221 | D199: Sarah Richardson | E199: PRD-0423 | F199: 1 | G199: 922.78 | H199: 0.0 | I199: Standard Ground | J199: B2B Portal | K199: REG-NA
A200: ORD-000094 | B200: 2024-11-17 | C200: CUST-00036 | D200: Mark Ramirez | E200: PRD-0294 | F200: 1 | G200: 159.21 | H200: 0.0 | I200: Express Air | J200: Affiliate Partner | K200: REG-APAC
A201: ORD-000094 | B201: 2024-11-17 | C201: CUST-00036 | D201: Mark Ramirez | E201: PRD-0381 | F201: 1 | G201: 321.45 | H201: 0.0 | I201: Express Air | J201: Affiliate Partner | K201: REG-APAC
A202: ORD-000094 | B202: 2024-11-17 | C202: CUST-00036 | D202: Mark Ramirez | E202: PRD-0309 | F202: 1 | G202: 632.18 | H202: 0.05 | I202: Express Air | J202: Affiliate Partner | K202: REG-APAC
A203: ORD-000094 | B203: 2024-11-17 | C203: CUST-00036 | D203: Mark Ramirez | E203: PRD-0490 | F203: 1 | G203: 146.89 | H203: 0.2 | I203: Express Air | J203: Affiliate Partner | K203: REG-APAC
A204: ORD-000094 | B204: 2024-11-17 | C204: CUST-00036 | D204: Mark Ramirez | E204: PRD-0437 | F204: 2 | G204: 177.29 | H204: 0.05 | I204: Express Air | J204: Affiliate Partner | K204: REG-APAC
A205: ORD-000095 | B205: 11/04/2023 | C205: CUST-02043 | D205: Eric Lewis | E205: PRD-0186 | F205: 1 | G205: 39.22 | H205: 0.1 | I205: Standard Ground | J205: Direct Web | K205: REG-EU
A206: ORD-000096 | B206: 2025-01-22 | C206: CUST-04182 | D206: Carolyn Hall | E206: PRD-0285 | F206: 2 | G206: 269.59 | H206: 0.1 | I206: Standard Ground | J206: Mobile App | K206: REG-EU
A207: ORD-000096 | B207: 2025-01-22 | C207: CUST-04182 | D207: Carolyn Hall | E207: PRD-0086 | F207: 1 | G207: 996.2 | H207: 0.1 | I207: Standard Ground | J207: Mobile App | K207: REG-EU
... A424: ORD-000205 | B424: 2024-02-13 | C424: CUST-04208 | D424: Nicole Price | E424: PRD-0303 | F424: 1 | G424: 61.92 | H424: 0.1 | I424: Standard Ground | J424: Affiliate Partner | K424: REG-NA
A425: ORD-000206 | B425: 2024-03-17 | E425: PRD-0186 | F425: 1 | G425: 39.22 | H425: 0.0 | I425: Standard Ground | J425: Direct Web
A426: ORD-000206 | B426: 2024-03-17 | E426: PRD-0282 | F426: 2 | G426: 48.43 | H426: 0.1 | I426: Standard Ground | J426: Direct Web
A427: ORD-000207 | B427: 2025-02-23 | C427: CUST-05650 | D427: Samuel Hernandez | E427: PRD-0336 | F427: 1 | G427: 216.76 | H427: 0.15 | I427: Standard Ground | J427: Direct Web | K427: REG-EU
A428: ORD-000208 | B428: 2025-11-19 | C428: CUST-06484 | D428: Raymond Lopez | E428: PRD-0372 | F428: 1 | G428: 519.61 | H428: 0.25 | I428: Express Air | J428: Direct Web | K428: REG-EU
A429: ORD-000209 | B429: 2024-05-26 | C429: CUST-01252 | D429: Sharon Bailey | E429: PRD-0305 | F429: 1 | G429: 713.99 | H429: 0.0 | I429: Standard Ground | J429: Direct Web | K429: REG-APAC
A430: ORD-000209 | B430: 2024-05-26 | C430: CUST-01252 | D430: Sharon Bailey | E430: PRD-0346 | F430: 1 | G430: 61.49 | H430: 0.0 | I430: Standard Ground | J430: Direct Web | K430: REG-APAC
A431: ORD-000210 | B431: 2025-09-19 | E431: PRD-0475 | F431: 2 | G431: 61.15 | H431: 0.0 | I431: Standard Ground | J431: Direct Web
A432: ORD-000210 | B432: 2025-09-19 | E432: PRD-0264 | F432: 2 | G432: 705.08 | H432: 0.05 | I432: Standard Ground | J432: Direct Web
A433: ORD-000210 | B433: 2025-09-19 | E433: PRD-0301 | F433: 2 | G433: 528.29 | H433: 0.1 | I433: Standard Ground | J433: Direct Web
A434: ORD-000210 | B434: 2025-09-19 | E434: PRD-0497 | F434: 1 | G434: 620.15 | H434: 0.05 | I434: Standard Ground | J434: Direct Web
A435: ORD-000211 | B435: 2025-11-01 | C435: CUST-01869 | D435: Sarah Robinson | E435: PRD-0418 | F435: 1 | G435: 287.35 | H435: 20% | I435: Standard Ground | J435: Mobile App | K435: REG-NA
A436: ORD-000211 | B436: 2025-11-01 | C436: CUST-01869 | D436: Sarah Robinson | E436: PRD-0376 | F436: 2 | G436: 219.88 | H436: 0.0 | I436: Standard Ground | J436: Mobile App | K436: REG-NA
A437: ORD-000211 | B437: 2025-11-01 | C437: CUST-01869 | D437: Sarah Robinson | E437: PRD-0294 | F437: 2 | G437: 159.21 | H437: 5% | I437: Standard Ground | J437: Mobile App | K437: REG-NA
A438: ORD-000212 | B438: 2023-08-04 | C438: CUST-01367 | D438: Gary Sanchez | E438: PRD-0171 | F438: 1 | G438: 143.61 | H438: 0.0 | I438: Freight | J438: Affiliate Partner | K438: REG-APAC
A439: ORD-000213 | B439: 2024-11-12 | C439: CUST-07855 | D439: Christine Cook | E439: PRD-0258 | F439: 1 | G439: 636.27 | H439: 0.25 | I439: Express Air | J439: Direct Web | K439: REG-NA
A440: ORD-000213 | B440: 2024-11-12 | C440: CUST-07855 | D440: Christine Cook | E440: PRD-0222 | F440: 1 | G440: 748.03 | H440: 0.05 | I440: Express Air | J440: Direct Web | K440: REG-NA
A441: ORD-000214 | B441: 2025-12-30 | C441: CUST-00969 | D441: Nicholas Gomez | E441: PRD-0044 | F441: 2 | G441: 24.94 | H441: 0.0 | I441: Freight | J441: Mobile App | K441: REG-NA
A442: ORD-000214 | B442: 2025-12-30 | C442: CUST-00969 | D442: Nicholas Gomez | E442: PRD-0066 | F442: 1 | G442: 976.53 | H442: 0.0 | I442: Freight | J442: Mobile App | K442: REG-NA
A443: ORD-000214 | B443: 2025-12-30 | C443: CUST-00969 | D443: Nicholas Gomez | E443: PRD-0499 | F443: 1 | G443: 1089.27 | H443: 0.15 | I443: Freight | J443: Mobile App | K443: REG-NA
A444: ORD-000214 | B444: 2025-12-30 | C444: CUST-00969 | D444: Nicholas Gomez | E444: PRD-0068 | F444: 1 | G444: 1340.27 | H444: 0.0 | I444: Freight | J444: Mobile App | K444: REG-NA
A445: ORD-000214 | B445: 2025-12-30 | C445: CUST-00969 | D445: Nicholas Gomez | E445: PRD-0167 | F445: 2 | G445: 606.81 | H445: 0.0 | I445: Freight | J445: Mobile App | K445: REG-NA
A446: ORD-000215 | B446: 2023-08-18 | C446: CUST-07558 | D446: Frank Ross | E446: PRD-0167 | F446: 1 | G446: 606.81 | H446: 0.2 | I446: Express Air | J446: Direct Web | K446: REG-NA
... A576: ORD-000280 | B576: 2025-06-09 | C576: CUST-03068 | D576: Ashley Lee | E576: PRD-0206 | F576: 3 | G576: 672.37 | H576: 0.0 | I576: Standard Ground | J576: Direct Web | K576: REG-NA
A577: ORD-000281 | B577: 2025-12-24 | E577: PRD-0265 | F577: 1 | G577: 426.8 | H577: 0.0 | I577: Same-Day Priority | J577: Affiliate Partner
A578: ORD-000282 | B578: 2024-12-17 | C578: CUST-06008 | D578: Benjamin Clark | E578: PRD-0332 | F578: 1 | G578: 82.03 | H578: 0.15 | I578: Standard Ground | J578: Mobile App | K578: REG-APAC
A579: ORD-000282 | B579: 2024-12-17 | C579: CUST-06008 | D579: Benjamin Clark | E579: PRD-0043 | F579: 1 | G579: 174.44 | H579: 0.0 | I579: Standard Ground | J579: Mobile App | K579: REG-APAC
A580: ORD-000282 | B580: 2024-12-17 | C580: CUST-06008 | D580: Benjamin Clark | E580: PRD-0172 | F580: 1 | G580: 132.43 | H580: 0.0 | I580: Standard Ground | J580: Mobile App | K580: REG-APAC
A581: ORD-000282 | B581: 2024-12-17 | C581: CUST-06008 | D581: Benjamin Clark | E581: PRD-0419 | F581: 2 | G581: 113.66 | H581: 0.25 | I581: Standard Ground | J581: Mobile App | K581: REG-APAC
A582: ORD-000283 | B582: 2025-05-09 | C582: CUST-07454 | D582: Kevin Morris | E582: PRD-0497 | F582: 5 | G582: 620.15 | H582: 0.0 | I582: Standard Ground | J582: Direct Web | K582: REG-NA
A583: ORD-000283 | B583: 2025-05-09 | C583: CUST-07454 | D583: Kevin Morris | E583: PRD-0084 | F583: 10 | G583: 72.68 | H583: 0.15 | I583: Standard Ground | J583: Direct Web | K583: REG-NA
A584: ORD-000284 | B584: 2023-09-29 | C584: CUST-01127 | D584: Diane Lopez | E584: PRD-0095 | F584: 3 | G584: 477.87 | H584: 0.0 | I584: Standard Ground | J584: Mobile App | K584: REG-NA
A585: ORD-000285 | B585: 2023-12-17 | C585: CUST-05980 | D585: Patricia Hall | E585: PRD-0400 | F585: 4 | G585: 409.11 | H585: 0.05 | I585: Standard Ground | J585: Direct Web | K585: REG-APAC
A586: ORD-000285 | B586: 2023-12-17 | C586: CUST-05980 | D586: Patricia Hall | E586: PRD-0092 | F586: 4 | G586: 63.9 | H586: 0.1 | I586: Standard Ground | J586: Direct Web | K586: REG-APAC
A587: ORD-000285 | B587: 2023-12-17 | C587: CUST-05980 | D587: Patricia Hall | E587: PRD-0405 | F587: 1 | G587: 29.36 | H587: 0.0 | I587: Standard Ground | J587: Direct Web | K587: REG-APAC
A588: ORD-000286 | B588: 2025-06-27 | C588: CUST-07688 | D588: Thomas Parker | E588: PRD-0018 | F588: 1 | G588: 75.52 | H588: 0.2 | I588: Same-Day Priority | J588: Direct Web | K588: REG-EU
A589: ORD-000286 | B589: 2025-06-27 | C589: CUST-07688 | D589: Thomas Parker | E589: PRD-0268 | F589: 1 | G589: 69.9 | H589: 0.05 | I589: Same-Day Priority | J589: Direct Web | K589: REG-EU
... A981: ORD-000489 | B981: 2023-12-22 | C981: CUST-07102 | D981: David Stewart | E981: PRD-0290 | F981: 1 | G981: 404.49 | H981: 0.1 | I981: Standard Ground | J981: Affiliate Partner | K981: REG-LATAM
A982: ORD-000490 | B982: 2024-03-12 | E982: PRD-0091 | F982: 1 | G982: 57.04 | H982: 0.05 | I982: Express Air | J982: Direct Web
A983: ORD-000490 | B983: 2024-03-12 | E983: PRD-0480 | F983: 1 | G983: 122.63 | H983: 0.0 | I983: Express Air | J983: Direct Web
A984: ORD-000490 | B984: 2024-03-12 | E984: PRD-0060 | F984: 4 | G984: 826.74 | H984: 0.05 | I984: Express Air | J984: Direct Web
A985: ORD-000491 | B985: 2023-03-20 | C985: CUST-03899 | D985: Jacob Howard | E985: PRD-0189 | F985: 1 | G985: 526.66 | H985: 0.0 | I985: Express Air | J985: Mobile App | K985: REG-NA
A986: ORD-000491 | B986: 2023-03-20 | C986: CUST-03899 | D986: Jacob Howard | E986: PRD-0184 | F986: 2 | G986: 79.57 | H986: 0.1 | I986: Express Air | J986: Mobile App | K986: REG-NA
...

Sheet 02_Data_Cleaning
A1: DATA AUDIT & CLEANSING TRANSFORMATION LAYER
A2: Illustrative formulas over sample rows; production cleaning is performed by scripts/clean_raw_datasets.py.
A3: Some demonstration formulas differ from production policy: missing customer keys are rejected by the Python pipeline, not imputed.
A4: Order_ID | B4: Clean_Date | C4: Clean_Customer_ID | D4: Clean_Customer_Name | E4: Clean_Quantity | F4: Clean_Unit_Price | G4: Clean_Discount_Rate | H4: Clean_Sales_Channel | I4: Clean_Region | J4: Data_Quality_Flag | K4: Audit_Action_Taken
A5: ='01_Raw_Data'!A5 | B5: =IFERROR(DATEVALUE('01_Raw_Data'!B5), IF('01_Raw_Data'!B5="", DATE(2024,1,1), '01_Raw_Data'!B5)) | C5: =IF(OR('01_Raw_Data'!C5="",'01_Raw_Data'!C5="0"), "CUST-GUEST", TRIM('01_Raw_Data'!C5)) | D5: =PROPER(TRIM(CLEAN('01_Raw_Data'!D5))) | E5: =ABS(IF(ISNUMBER(VALUE('01_Raw_Data'!F5)), VALUE('01_Raw_Data'!F5), 1)) | F5: ='01_Raw_Data'!G5 | G5: =IF(ISNUMBER('01_Raw_Data'!H5), '01_Raw_Data'!H5, IFERROR(VALUE(SUBSTITUTE('01_Raw_Data'!H5, "%", ""))/100, 0)) | H5: =PROPER(TRIM('01_Raw_Data'!J5)) | I5: =IF('01_Raw_Data'!K5="", "REG-NA", UPPER(TRIM('01_Raw_Data'!K5))) | J5: =IF(OR('01_Raw_Data'!C5="", '01_Raw_Data'!F5<0, ISNUMBER(SEARCH("%", '01_Raw_Data'!H5))), "FIXED ANOMALY", "PASSED") | K5: =IF('01_Raw_Data'!F5<0, "Converted Negative Quantity to ABS", IF('01_Raw_Data'!C5="", "Imputed Missing Customer ID", IF(ISNUMBER(SEARCH("%", '01_Raw_Data'!H5)), "Parsed Text % to Numeric Rate", "Standardized Format")))
A6: ='01_Raw_Data'!A6 | B6: =IFERROR(DATEVALUE('01_Raw_Data'!B6), IF('01_Raw_Data'!B6="", DATE(2024,1,1), '01_Raw_Data'!B6)) | C6: =IF(OR('01_Raw_Data'!C6="",'01_Raw_Data'!C6="0"), "CUST-GUEST", TRIM('01_Raw_Data'!C6)) | D6: =PROPER(TRIM(CLEAN('01_Raw_Data'!D6))) | E6: =ABS(IF(ISNUMBER(VALUE('01_Raw_Data'!F6)), VALUE('01_Raw_Data'!F6), 1)) | F6: ='01_Raw_Data'!G6 | G6: =IF(ISNUMBER('01_Raw_Data'!H6), '01_Raw_Data'!H6, IFERROR(VALUE(SUBSTITUTE('01_Raw_Data'!H6, "%", ""))/100, 0)) | H6: =PROPER(TRIM('01_Raw_Data'!J6)) | I6: =IF('01_Raw_Data'!K6="", "REG-NA", UPPER(TRIM('01_Raw_Data'!K6))) | J6: =IF(OR('01_Raw_Data'!C6="", '01_Raw_Data'!F6<0, ISNUMBER(SEARCH("%", '01_Raw_Data'!H6))), "FIXED ANOMALY", "PASSED") | K6: =IF('01_Raw_Data'!F6<0, "Converted Negative Quantity to ABS", IF('01_Raw_Data'!C6="", "Imputed Missing Customer ID", IF(ISNUMBER(SEARCH("%", '01_Raw_Data'!H6)), "Parsed Text % to Numeric Rate", "Standardized Format")))
A7: ='01_Raw_Data'!A7 | B7: =IFERROR(DATEVALUE('01_Raw_Data'!B7), IF('01_Raw_Data'!B7="", DATE(2024,1,1), '01_Raw_Data'!B7)) | C7: =IF(OR('01_Raw_Data'!C7="",'01_Raw_Data'!C7="0"), "CUST-GUEST", TRIM('01_Raw_Data'!C7)) | D7: =PROPER(TRIM(CLEAN('01_Raw_Data'!D7))) | E7: =ABS(IF(ISNUMBER(VALUE('01_Raw_Data'!F7)), VALUE('01_Raw_Data'!F7), 1)) | F7: ='01_Raw_Data'!G7 | G7: =IF(ISNUMBER('01_Raw_Data'!H7), '01_Raw_Data'!H7, IFERROR(VALUE(SUBSTITUTE('01_Raw_Data'!H7, "%", ""))/100, 0)) | H7: =PROPER(TRIM('01_Raw_Data'!J7)) | I7: =IF('01_Raw_Data'!K7="", "REG-NA", UPPER(TRIM('01_Raw_Data'!K7))) | J7: =IF(OR('01_Raw_Data'!C7="", '01_Raw_Data'!F7<0, ISNUMBER(SEARCH("%", '01_Raw_Data'!H7))), "FIXED ANOMALY", "PASSED") | K7: =IF('01_Raw_Data'!F7<0, "Converted Negative Quantity to ABS", IF('01_Raw_Data'!C7="", "Imputed Missing Customer ID", IF(ISNUMBER(SEARCH("%", '01_Raw_Data'!H7)), "Parsed Text % to Numeric Rate", "Standardized Format")))
A8: ='01_Raw_Data'!A8 | B8: =IFERROR(DATEVALUE('01_Raw_Data'!B8), IF('01_Raw_Data'!B8="", DATE(2024,1,1), '01_Raw_Data'!B8)) | C8: =IF(OR('01_Raw_Data'!C8="",'01_Raw_Data'!C8="0"), "CUST-GUEST", TRIM('01_Raw_Data'!C8)) | D8: =PROPER(TRIM(CLEAN('01_Raw_Data'!D8))) | E8: =ABS(IF(ISNUMBER(VALUE('01_Raw_Data'!F8)), VALUE('01_Raw_Data'!F8), 1)) | F8: ='01_Raw_Data'!G8 | G8: =IF(ISNUMBER('01_Raw_Data'!H8), '01_Raw_Data'!H8, IFERROR(VALUE(SUBSTITUTE('01_Raw_Data'!H8, "%", ""))/100, 0)) | H8: =PROPER(TRIM('01_Raw_Data'!J8)) | I8: =IF('01_Raw_Data'!K8="", "REG-NA", UPPER(TRIM('01_Raw_Data'!K8))) | J8: =IF(OR('01_Raw_Data'!C8="", '01_Raw_Data'!F8<0, ISNUMBER(SEARCH("%", '01_Raw_Data'!H8))), "FIXED ANOMALY", "PASSED") | K8: =IF('01_Raw_Data'!F8<0, "Converted Negative Quantity to ABS", IF('01_Raw_Data'!C8="", "Imputed Missing Customer ID", IF(ISNUMBER(SEARCH("%", '01_Raw_Data'!H8)), "Parsed Text % to Numeric Rate", "Standardized Format")))
A9: ='01_Raw_Data'!A9 | B9: =IFERROR(DATEVALUE('01_Raw_Data'!B9), IF('01_Raw_Data'!B9="", DATE(2024,1,1), '01_Raw_Data'!B9)) | C9: =IF(OR('01_Raw_Data'!C9="",'01_Raw_Data'!C9="0"), "CUST-GUEST", TRIM('01_Raw_Data'!C9)) | D9: =PROPER(TRIM(CLEAN('01_Raw_Data'!D9))) | E9: =ABS(IF(ISNUMBER(VALUE('01_Raw_Data'!F9)), VALUE('01_Raw_Data'!F9), 1)) | F9: ='01_Raw_Data'!G9 | G9: =IF(ISNUMBER('01_Raw_Data'!H9), '01_Raw_Data'!H9, IFERROR(VALUE(SUBSTITUTE('01_Raw_Data'!H9, "%", ""))/100, 0)) | H9: =PROPER(TRIM('01_Raw_Data'!J9)) | I9: =IF('01_Raw_Data'!K9="", "REG-NA", UPPER(TRIM('01_Raw_Data'!K9))) | J9: =IF(OR('01_Raw_Data'!C9="", '01_Raw_Data'!F9<0, ISNUMBER(SEARCH("%", '01_Raw_Data'!H9))), "FIXED ANOMALY", "PASSED") | K9: =IF('01_Raw_Data'!F9<0, "Converted Negative Quantity to ABS", IF('01_Raw_Data'!C9="", "Imputed Missing Customer ID", IF(ISNUMBER(SEARCH("%", '01_Raw_Data'!H9)), "Parsed Text % to Numeric Rate", "Standardized Format")))
A10: ='01_Raw_Data'!A10 | B10: =IFERROR(DATEVALUE('01_Raw_Data'!B10), IF('01_Raw_Data'!B10="", DATE(2024,1,1), '01_Raw_Data'!B10)) | C10: =IF(OR('01_Raw_Data'!C10="",'01_Raw_Data'!C10="0"), "CUST-GUEST", TRIM('01_Raw_Data'!C10)) | D10: =PROPER(TRIM(CLEAN('01_Raw_Data'!D10))) | E10: =ABS(IF(ISNUMBER(VALUE('01_Raw_Data'!F10)), VALUE('01_Raw_Data'!F10), 1)) | F10: ='01_Raw_Data'!G10 | G10: =IF(ISNUMBER('01_Raw_Data'!H10), '01_Raw_Data'!H10, IFERROR(VALUE(SUBSTITUTE('01_Raw_Data'!H10, "%", ""))/100, 0)) | H10: =PROPER(TRIM('01_Raw_Data'!J10)) | I10: =IF('01_Raw_Data'!K10="", "REG-NA", UPPER(TRIM('01_Raw_Data'!K10))) | J10: =IF(OR('01_Raw_Data'!C10="", '01_Raw_Data'!F10<0, ISNUMBER(SEARCH("%", '01_Raw_Data'!H10))), "FIXED ANOMALY", "PASSED") | K10: =IF('01_Raw_Data'!F10<0, "Converted Negative Quantity to ABS", IF('01_Raw_Data'!C10="", "Imputed Missing Customer ID", IF(ISNUMBER(SEARCH("%", '01_Raw_Data'!H10)), "Parsed Text % to Numeric Rate", "Standardized Format")))
A11: ='01_Raw_Data'!A11 | B11: =IFERROR(DATEVALUE('01_Raw_Data'!B11), IF('01_Raw_Data'!B11="", DATE(2024,1,1), '01_Raw_Data'!B11)) | C11: =IF(OR('01_Raw_Data'!C11="",'01_Raw_Data'!C11="0"), "CUST-GUEST", TRIM('01_Raw_Data'!C11)) | D11: =PROPER(TRIM(CLEAN('01_Raw_Data'!D11))) | E11: =ABS(IF(ISNUMBER(VALUE('01_Raw_Data'!F11)), VALUE('01_Raw_Data'!F11), 1)) | F11: ='01_Raw_Data'!G11 | G11: =IF(ISNUMBER('01_Raw_Data'!H11), '01_Raw_Data'!H11, IFERROR(VALUE(SUBSTITUTE('01_Raw_Data'!H11, "%", ""))/100, 0)) | H11: =PROPER(TRIM('01_Raw_Data'!J11)) | I11: =IF('01_Raw_Data'!K11="", "REG-NA", UPPER(TRIM('01_Raw_Data'!K11))) | J11: =IF(OR('01_Raw_Data'!C11="", '01_Raw_Data'!F11<0, ISNUMBER(SEARCH("%", '01_Raw_Data'!H11))), "FIXED ANOMALY", "PASSED") | K11: =IF('01_Raw_Data'!F11<0, "Converted Negative Quantity to ABS", IF('01_Raw_Data'!C11="", "Imputed Missing Customer ID", IF(ISNUMBER(SEARCH("%", '01_Raw_Data'!H11)), "Parsed Text % to Numeric Rate", "Standardized Format")))
A12: ='01_Raw_Data'!A12 | B12: =IFERROR(DATEVALUE('01_Raw_Data'!B12), IF('01_Raw_Data'!B12="", DATE(2024,1,1), '01_Raw_Data'!B12)) | C12: =IF(OR('01_Raw_Data'!C12="",'01_Raw_Data'!C12="0"), "CUST-GUEST", TRIM('01_Raw_Data'!C12)) | D12: =PROPER(TRIM(CLEAN('01_Raw_Data'!D12))) | E12: =ABS(IF(ISNUMBER(VALUE('01_Raw_Data'!F12)), VALUE('01_Raw_Data'!F12), 1)) | F12: ='01_Raw_Data'!G12 | G12: =IF(ISNUMBER('01_Raw_Data'!H12), '01_Raw_Data'!H12, IFERROR(VALUE(SUBSTITUTE('01_Raw_Data'!H12, "%", ""))/100, 0)) | H12: =PROPER(TRIM('01_Raw_Data'!J12)) | I12: =IF('01_Raw_Data'!K12="", "REG-NA", UPPER(TRIM('01_Raw_Data'!K12))) | J12: =IF(OR('01_Raw_Data'!C12="", '01_Raw_Data'!F12<0, ISNUMBER(SEARCH("%", '01_Raw_Data'!H12))), "FIXED ANOMALY", "PASSED") | K12: =IF('01_Raw_Data'!F12<0, "Converted Negative Quantity to ABS", IF('01_Raw_Data'!C12="", "Imputed Missing Customer ID", IF(ISNUMBER(SEARCH("%", '01_Raw_Data'!H12)), "Parsed Text % to Numeric Rate", "Standardized Format")))
A13: ='01_Raw_Data'!A13 | B13: =IFERROR(DATEVALUE('01_Raw_Data'!B13), IF('01_Raw_Data'!B13="", DATE(2024,1,1), '01_Raw_Data'!B13)) | C13: =IF(OR('01_Raw_Data'!C13="",'01_Raw_Data'!C13="0"), "CUST-GUEST", TRIM('01_Raw_Data'!C13)) | D13: =PROPER(TRIM(CLEAN('01_Raw_Data'!D13))) | E13: =ABS(IF(ISNUMBER(VALUE('01_Raw_Data'!F13)), VALUE('01_Raw_Data'!F13), 1)) | F13: ='01_Raw_Data'!G13 | G13: =IF(ISNUMBER('01_Raw_Data'!H13), '01_Raw_Data'!H13, IFERROR(VALUE(SUBSTITUTE('01_Raw_Data'!H13, "%", ""))/100, 0)) | H13: =PROPER(TRIM('01_Raw_Data'!J13)) | I13: =IF('01_Raw_Data'!K13="", "REG-NA", UPPER(TRIM('01_Raw_Data'!K13))) | J13: =IF(OR('01_Raw_Data'!C13="", '01_Raw_Data'!F13<0, ISNUMBER(SEARCH("%", '01_Raw_Data'!H13))), "FIXED ANOMALY", "PASSED") | K13: =IF('01_Raw_Data'!F13<0, "Converted Negative Quantity to ABS", IF('01_Raw_Data'!C13="", "Imputed Missing Customer ID", IF(ISNUMBER(SEARCH("%", '01_Raw_Data'!H13)), "Parsed Text % to Numeric Rate", "Standardized Format")))
A14: ='01_Raw_Data'!A14 | B14: =IFERROR(DATEVALUE('01_Raw_Data'!B14), IF('01_Raw_Data'!B14="", DATE(2024,1,1), '01_Raw_Data'!B14)) | C14: =IF(OR('01_Raw_Data'!C14="",'01_Raw_Data'!C14="0"), "CUST-GUEST", TRIM('01_Raw_Data'!C14)) | D14: =PROPER(TRIM(CLEAN('01_Raw_Data'!D14))) | E14: =ABS(IF(ISNUMBER(VALUE('01_Raw_Data'!F14)), VALUE('01_Raw_Data'!F14), 1)) | F14: ='01_Raw_Data'!G14 | G14: =IF(ISNUMBER('01_Raw_Data'!H14), '01_Raw_Data'!H14, IFERROR(VALUE(SUBSTITUTE('01_Raw_Data'!H14, "%", ""))/100, 0)) | H14: =PROPER(TRIM('01_Raw_Data'!J14)) | I14: =IF('01_Raw_Data'!K14="", "REG-NA", UPPER(TRIM('01_Raw_Data'!K14))) | J14: =IF(OR('01_Raw_Data'!C14="", '01_Raw_Data'!F14<0, ISNUMBER(SEARCH("%", '01_Raw_Data'!H14))), "FIXED ANOMALY", "PASSED") | K14: =IF('01_Raw_Data'!F14<0, "Converted Negative Quantity to ABS", IF('01_Raw_Data'!C14="", "Imputed Missing Customer ID", IF(ISNUMBER(SEARCH("%", '01_Raw_Data'!H14)), "Parsed Text % to Numeric Rate", "Standardized Format")))
A15: ='01_Raw_Data'!A15 | B15: =IFERROR(DATEVALUE('01_Raw_Data'!B15), IF('01_Raw_Data'!B15="", DATE(2024,1,1), '01_Raw_Data'!B15)) | C15: =IF(OR('01_Raw_Data'!C15="",'01_Raw_Data'!C15="0"), "CUST-GUEST", TRIM('01_Raw_Data'!C15)) | D15: =PROPER(TRIM(CLEAN('01_Raw_Data'!D15))) | E15: =ABS(IF(ISNUMBER(VALUE('01_Raw_Data'!F15)), VALUE('01_Raw_Data'!F15), 1)) | F15: ='01_Raw_Data'!G15 | G15: =IF(ISNUMBER('01_Raw_Data'!H15), '01_Raw_Data'!H15, IFERROR(VALUE(SUBSTITUTE('01_Raw_Data'!H15, "%", ""))/100, 0)) | H15: =PROPER(TRIM('01_Raw_Data'!J15)) | I15: =IF('01_Raw_Data'!K15="", "REG-NA", UPPER(TRIM('01_Raw_Data'!K15))) | J15: =IF(OR('01_Raw_Data'!C15="", '01_Raw_Data'!F15<0, ISNUMBER(SEARCH("%", '01_Raw_Data'!H15))), "FIXED ANOMALY", "PASSED") | K15: =IF('01_Raw_Data'!F15<0, "Converted Negative Quantity to ABS", IF('01_Raw_Data'!C15="", "Imputed Missing Customer ID", IF(ISNUMBER(SEARCH("%", '01_Raw_Data'!H15)), "Parsed Text % to Numeric Rate", "Standardized Format")))
A16: ='01_Raw_Data'!A16 | B16: =IFERROR(DATEVALUE('01_Raw_Data'!B16), IF('01_Raw_Data'!B16="", DATE(2024,1,1), '01_Raw_Data'!B16)) | C16: =IF(OR('01_Raw_Data'!C16="",'01_Raw_Data'!C16="0"), "CUST-GUEST", TRIM('01_Raw_Data'!C16)) | D16: =PROPER(TRIM(CLEAN('01_Raw_Data'!D16))) | E16: =ABS(IF(ISNUMBER(VALUE('01_Raw_Data'!F16)), VALUE('01_Raw_Data'!F16), 1)) | F16: ='01_Raw_Data'!G16 | G16: =IF(ISNUMBER('01_Raw_Data'!H16), '01_Raw_Data'!H16, IFERROR(VALUE(SUBSTITUTE('01_Raw_Data'!H16, "%", ""))/100, 0)) | H16: =PROPER(TRIM('01_Raw_Data'!J16)) | I16: =IF('01_Raw_Data'!K16="", "REG-NA", UPPER(TRIM('01_Raw_Data'!K16))) | J16: =IF(OR('01_Raw_Data'!C16="", '01_Raw_Data'!F16<0, ISNUMBER(SEARCH("%", '01_Raw_Data'!H16))), "FIXED ANOMALY", "PASSED") | K16: =IF('01_Raw_Data'!F16<0, "Converted Negative Quantity to ABS", IF('01_Raw_Data'!C16="", "Imputed Missing Customer ID", IF(ISNUMBER(SEARCH("%", '01_Raw_Data'!H16)), "Parsed Text % to Numeric Rate", "Standardized Format")))
... A504: ='01_Raw_Data'!A504 | B504: =IFERROR(DATEVALUE('01_Raw_Data'!B504), IF('01_Raw_Data'!B504="", DATE(2024,1,1), '01_Raw_Data'!B504)) | C504: =IF(OR('01_Raw_Data'!C504="",'01_Raw_Data'!C504="0"), "CUST-GUEST", TRIM('01_Raw_Data'!C504)) | D504: =PROPER(TRIM(CLEAN('01_Raw_Data'!D504))) | E504: =ABS(IF(ISNUMBER(VALUE('01_Raw_Data'!F504)), VALUE('01_Raw_Data'!F504), 1)) | F504: ='01_Raw_Data'!G504 | G504: =IF(ISNUMBER('01_Raw_Data'!H504), '01_Raw_Data'!H504, IFERROR(VALUE(SUBSTITUTE('01_Raw_Data'!H504, "%", ""))/100, 0)) | H504: =PROPER(TRIM('01_Raw_Data'!J504)) | I504: =IF('01_Raw_Data'!K504="", "REG-NA", UPPER(TRIM('01_Raw_Data'!K504))) | J504: =IF(OR('01_Raw_Data'!C504="", '01_Raw_Data'!F504<0, ISNUMBER(SEARCH("%", '01_Raw_Data'!H504))), "FIXED ANOMALY", "PASSED") | K504: =IF('01_Raw_Data'!F504<0, "Converted Negative Quantity to ABS", IF('01_Raw_Data'!C504="", "Imputed Missing Customer ID", IF(ISNUMBER(SEARCH("%", '01_Raw_Data'!H504)), "Parsed Text % to Numeric Rate", "Standardized Format")))

Sheet 03_Customers
A1: CUSTOMER MASTER & SEGMENTATION PROFILE
A2: Demographic segmentation using IFS/LOOKUP formulas and order aggregation metrics.
A4: Customer_ID | B4: Customer_Name | C4: Gender | D4: Age | E4: Age_Group | F4: City | G4: State | H4: Region_ID | I4: Customer_Segment | J4: Customer_Since | K4: Total_Orders | L4: Total_Spend | M4: Customer_Tier
A5: CUST-00001 | B5: Gary Watson | C5: Male | D5: 46 | E5: =IF(D5<25, "18-24", IF(D5<35, "25-34", IF(D5<50, "35-49", "50+"))) | F5: Melbourne | G5: Victoria | H5: REG-APAC | I5: Consumer | J5: 2024-02-22 | K5: =COUNTIFS('05_Orders'!$C:$C, A5) | L5: =SUMIFS('05_Orders'!$I:$I, '05_Orders'!$C:$C, A5) | M5: =IF(L5>=2000, "Platinum VIP", IF(L5>=1000, "Gold", IF(L5>=500, "Silver", "Standard")))
A6: CUST-00002 | B6: George Gray | C6: Other | D6: 30 | E6: =IF(D6<25, "18-24", IF(D6<35, "25-34", IF(D6<50, "35-49", "50+"))) | F6: Dublin | G6: Leinster | H6: REG-EU | I6: Consumer | J6: 2025-05-18 | K6: =COUNTIFS('05_Orders'!$C:$C, A6) | L6: =SUMIFS('05_Orders'!$I:$I, '05_Orders'!$C:$C, A6) | M6: =IF(L6>=2000, "Platinum VIP", IF(L6>=1000, "Gold", IF(L6>=500, "Silver", "Standard")))
A7: CUST-00003 | B7: Cynthia Hernandez | C7: Female | D7: 57 | E7: =IF(D7<25, "18-24", IF(D7<35, "25-34", IF(D7<50, "35-49", "50+"))) | F7: Chicago | G7: Illinois | H7: REG-NA | I7: Home Office | J7: 2024-08-04 | K7: =COUNTIFS('05_Orders'!$C:$C, A7) | L7: =SUMIFS('05_Orders'!$I:$I, '05_Orders'!$C:$C, A7) | M7: =IF(L7>=2000, "Platinum VIP", IF(L7>=1000, "Gold", IF(L7>=500, "Silver", "Standard")))
A8: CUST-00004 | B8: Elizabeth Hernandez | C8: Male | D8: 39 | E8: =IF(D8<25, "18-24", IF(D8<35, "25-34", IF(D8<50, "35-49", "50+"))) | F8: Seattle | G8: Washington | H8: REG-NA | I8: Corporate | J8: 2024-12-25 | K8: =COUNTIFS('05_Orders'!$C:$C, A8) | L8: =SUMIFS('05_Orders'!$I:$I, '05_Orders'!$C:$C, A8) | M8: =IF(L8>=2000, "Platinum VIP", IF(L8>=1000, "Gold", IF(L8>=500, "Silver", "Standard")))
A9: CUST-00005 | B9: Edward Myers | C9: Other | D9: 51 | E9: =IF(D9<25, "18-24", IF(D9<35, "25-34", IF(D9<50, "35-49", "50+"))) | F9: Buenos Aires | G9: Buenos Aires | H9: REG-LATAM | I9: Consumer | J9: 2021-02-17 | K9: =COUNTIFS('05_Orders'!$C:$C, A9) | L9: =SUMIFS('05_Orders'!$I:$I, '05_Orders'!$C:$C, A9) | M9: =IF(L9>=2000, "Platinum VIP", IF(L9>=1000, "Gold", IF(L9>=500, "Silver", "Standard")))
A10: CUST-00006 | B10: Ruth Hernandez | C10: Male | D10: 28 | E10: =IF(D10<25, "18-24", IF(D10<35, "25-34", IF(D10<50, "35-49", "50+"))) | F10: Los Angeles | G10: California | H10: REG-NA | I10: Consumer | J10: 2023-08-28 | K10: =COUNTIFS('05_Orders'!$C:$C, A10) | L10: =SUMIFS('05_Orders'!$I:$I, '05_Orders'!$C:$C, A10) | M10: =IF(L10>=2000, "Platinum VIP", IF(L10>=1000, "Gold", IF(L10>=500, "Silver", "Standard")))
A11: CUST-00007 | B11: David Wilson | C11: Female | D11: 57 | E11: =IF(D11<25, "18-24", IF(D11<35, "25-34", IF(D11<50, "35-49", "50+"))) | F11: Atlanta | G11: Georgia | H11: REG-NA | I11: Consumer | J11: 2022-05-22 | K11: =COUNTIFS('05_Orders'!$C:$C, A11) | L11: =SUMIFS('05_Orders'!$I:$I, '05_Orders'!$C:$C, A11) | M11: =IF(L11>=2000, "Platinum VIP", IF(L11>=1000, "Gold", IF(L11>=500, "Silver", "Standard")))
A12: CUST-00008 | B12: Nancy Brown | C12: Male | D12: 60 | E12: =IF(D12<25, "18-24", IF(D12<35, "25-34", IF(D12<50, "35-49", "50+"))) | F12: Seattle | G12: Washington | H12: REG-NA | I12: Home Office | J12: 2023-08-15 | K12: =COUNTIFS('05_Orders'!$C:$C, A12) | L12: =SUMIFS('05_Orders'!$I:$I, '05_Orders'!$C:$C, A12) | M12: =IF(L12>=2000, "Platinum VIP", IF(L12>=1000, "Gold", IF(L12>=500, "Silver", "Standard")))
A13: CUST-00009 | B13: Catherine Cooper | C13: Male | D13: 55 | E13: =IF(D13<25, "18-24", IF(D13<35, "25-34", IF(D13<50, "35-49", "50+"))) | F13: Stockholm | G13: Stockholm County | H13: REG-EU | I13: Consumer | J13: 2024-08-03 | K13: =COUNTIFS('05_Orders'!$C:$C, A13) | L13: =SUMIFS('05_Orders'!$I:$I, '05_Orders'!$C:$C, A13) | M13: =IF(L13>=2000, "Platinum VIP", IF(L13>=1000, "Gold", IF(L13>=500, "Silver", "Standard")))
A14: CUST-00010 | B14: Barbara Cruz | C14: Female | D14: 41 | E14: =IF(D14<25, "18-24", IF(D14<35, "25-34", IF(D14<50, "35-49", "50+"))) | F14: Chicago | G14: Illinois | H14: REG-NA | I14: Consumer | J14: 2021-01-01 | K14: =COUNTIFS('05_Orders'!$C:$C, A14) | L14: =SUMIFS('05_Orders'!$I:$I, '05_Orders'!$C:$C, A14) | M14: =IF(L14>=2000, "Platinum VIP", IF(L14>=1000, "Gold", IF(L14>=500, "Silver", "Standard")))
A15: CUST-00011 | B15: Stephen Johnson | C15: Other | D15: 49 | E15: =IF(D15<25, "18-24", IF(D15<35, "25-34", IF(D15<50, "35-49", "50+"))) | F15: Lima | G15: Lima Province | H15: REG-LATAM | I15: Consumer | J15: 2025-04-18 | K15: =COUNTIFS('05_Orders'!$C:$C, A15) | L15: =SUMIFS('05_Orders'!$I:$I, '05_Orders'!$C:$C, A15) | M15: =IF(L15>=2000, "Platinum VIP", IF(L15>=1000, "Gold", IF(L15>=500, "Silver", "Standard")))
A16: CUST-00012 | B16: Deborah Harris | C16: Female | D16: 53 | E16: =IF(D16<25, "18-24", IF(D16<35, "25-34", IF(D16<50, "35-49", "50+"))) | F16: Munich | G16: Bavaria | H16: REG-EU | I16: Consumer | J16: 2025-02-18 | K16: =COUNTIFS('05_Orders'!$C:$C, A16) | L16: =SUMIFS('05_Orders'!$I:$I, '05_Orders'!$C:$C, A16) | M16: =IF(L16>=2000, "Platinum VIP", IF(L16>=1000, "Gold", IF(L16>=500, "Silver", "Standard")))
... A1004: CUST-01000 | B1004: Ashley Flores | C1004: Other | D1004: 70 | E1004: =IF(D1004<25, "18-24", IF(D1004<35, "25-34", IF(D1004<50, "35-49", "50+"))) | F1004: London | G1004: Greater London | H1004: REG-EU | I1004: Home Office | J1004: 2021-04-23 | K1004: =COUNTIFS('05_Orders'!$C:$C, A1004) | L1004: =SUMIFS('05_Orders'!$I:$I, '05_Orders'!$C:$C, A1004) | M1004: =IF(L1004>=2000, "Platinum VIP", IF(L1004>=1000, "Gold", IF(L1004>=500, "Silver", "Standard")))

Sheet 04_Products
A1: PRODUCT CATALOG & MARGIN MATRIX
A2: SKU pricing tiers, base cost, list selling price, gross margin %, and reorder alert flags.
A4: Product_ID | B4: Product_Name | C4: Category | D4: Sub_Category | E4: Brand | F4: Cost_Price | G4: Selling_Price | H4: Markup_Amount | I4: Gross_Margin_Pct | J4: Price_Tier | K4: Reorder_Level
A5: PRD-0001 | B5: OptimaPrint Pens, Inks & Marker Model-242 | C5: Office Supplies | D5: Pens, Inks & Markers | E5: OptimaPrint | F5: 5.51 | G5: 9 | H5: =G5-F5 | I5: =IFERROR(H5/G5, 0) | J5: =IF(G5>=400, "High-End", IF(G5>=100, "Mid-Tier", "Economy")) | K5: 35
A6: PRD-0002 | B6: ErgoComfort Standing Desk Model-716 | C6: Furniture | D6: Standing Desks | E6: ErgoComfort | F6: 63.03 | G6: 91.41 | H6: =G6-F6 | I6: =IFERROR(H6/G6, 0) | J6: =IF(G6>=400, "High-End", IF(G6>=100, "Mid-Tier", "Economy")) | K6: 100
A7: PRD-0003 | B7: ZenithLogix Monitors & Display Model-877 | C7: Technology | D7: Monitors & Displays | E7: ZenithLogix | F7: 574.18 | G7: 807.39 | H7: =G7-F7 | I7: =IFERROR(H7/G7, 0) | J7: =IF(G7>=400, "High-End", IF(G7>=100, "Mid-Tier", "Economy")) | K7: 20
A8: PRD-0004 | B8: AccuBinder Desk Accessorie Model-967 | C8: Office Supplies | D8: Desk Accessories | E8: AccuBinder | F8: 8.64 | G8: 13.71 | H8: =G8-F8 | I8: =IFERROR(H8/G8, 0) | J8: =IF(G8>=400, "High-End", IF(G8>=100, "Mid-Tier", "Economy")) | K8: 50
A9: PRD-0005 | B9: ZenithLogix Smartphones & Accessorie Model-733 | C9: Technology | D9: Smartphones & Accessories | E9: ZenithLogix | F9: 107.1 | G9: 148.59 | H9: =G9-F9 | I9: =IFERROR(H9/G9, 0) | J9: =IF(G9>=400, "High-End", IF(G9>=100, "Mid-Tier", "Economy")) | K9: 150
A10: PRD-0006 | B10: EverWrite Pens, Inks & Marker Model-987 | C10: Office Supplies | D10: Pens, Inks & Markers | E10: EverWrite | F10: 35.81 | G10: 64.34 | H10: =G10-F10 | I10: =IFERROR(H10/G10, 0) | J10: =IF(G10>=400, "High-End", IF(G10>=100, "Mid-Tier", "Economy")) | K10: 35
A11: PRD-0007 | B11: NordicCraft Office Chair Model-763 | C11: Furniture | D11: Office Chairs | E11: NordicCraft | F11: 171.75 | G11: 254.43 | H11: =G11-F11 | I11: =IFERROR(H11/G11, 0) | J11: =IF(G11>=400, "High-End", IF(G11>=100, "Mid-Tier", "Economy")) | K11: 150
A12: PRD-0008 | B12: ModuDesk Bookcases & Storage Model-670 | C12: Furniture | D12: Bookcases & Storage | E12: ModuDesk | F12: 208.32 | G12: 323.49 | H12: =G12-F12 | I12: =IFERROR(H12/G12, 0) | J12: =IF(G12>=400, "High-End", IF(G12>=100, "Mid-Tier", "Economy")) | K12: 150
A13: PRD-0009 | B13: UrbanShield Corporate Apparel Model-316 | C13: Apparel & Gear | D13: Corporate Apparel | E13: UrbanShield | F13: 115.63 | G13: 186.43 | H13: =G13-F13 | I13: =IFERROR(H13/G13, 0) | J13: =IF(G13>=400, "High-End", IF(G13>=100, "Mid-Tier", "Economy")) | K13: 20
A14: PRD-0010 | B14: ModuDesk Bookcases & Storage Model-371 | C14: Furniture | D14: Bookcases & Storage | E14: ModuDesk | F14: 580.23 | G14: 863.3 | H14: =G14-F14 | I14: =IFERROR(H14/G14, 0) | J14: =IF(G14>=400, "High-End", IF(G14>=100, "Mid-Tier", "Economy")) | K14: 35
A15: PRD-0011 | B15: Kinetix Standing Desk Model-621 | C15: Furniture | D15: Standing Desks | E15: Kinetix | F15: 286.64 | G15: 415.76 | H15: =G15-F15 | I15: =IFERROR(H15/G15, 0) | J15: =IF(G15>=400, "High-End", IF(G15>=100, "Mid-Tier", "Economy")) | K15: 35
A16: PRD-0012 | B16: Hyperion Audio & Headphone Model-710 | C16: Technology | D16: Audio & Headphones | E16: Hyperion | F16: 421.28 | G16: 583.31 | H16: =G16-F16 | I16: =IFERROR(H16/G16, 0) | J16: =IF(G16>=400, "High-End", IF(G16>=100, "Mid-Tier", "Economy")) | K16: 75
... A504: PRD-0500 | B504: EcoPaper Desk Accessorie Model-148 | C504: Office Supplies | D504: Desk Accessories | E504: EcoPaper | F504: 16.65 | G504: 27.13 | H504: =G504-F504 | I504: =IFERROR(H504/G504, 0) | J504: =IF(G504>=400, "High-End", IF(G504>=100, "Mid-Tier", "Economy")) | K504: 100

Sheet 05_Orders
A1: ANALYTICAL ORDERS BASE TABLE
A2: Normalized transactional table with dynamic XLOOKUP, line revenue, cost, profit, and margin formulas.
A4: Order_Detail_ID | B4: Order_ID | C4: Order_Date | D4: Customer_ID | E4: Product_ID | F4: Quantity | G4: Unit_Price | H4: Unit_Cost | I4: Gross_Sales | J4: Discount_Rate | K4: Discount_Amount | L4: Net_Sales | M4: Total_Cost | N4: Net_Profit | O4: Profit_Margin_Pct | P4: Order_Year | Q4: Order_Month | R4: Sales_Channel | S4: Region_ID
A5: DTL-0000001 | B5: ORD-000001 | C5: 2025-03-14 | D5: CUST-03473 | E5: PRD-0308 | F5: 1 | G5: =IFERROR(XLOOKUP(E5, '04_Products'!$A:$A, '04_Products'!$G:$G), 61.03) | H5: =IFERROR(XLOOKUP(E5, '04_Products'!$A:$A, '04_Products'!$F:$F), 0) | I5: =F5*G5 | J5: 0.05 | K5: =I5*J5 | L5: =I5-K5 | M5: =F5*H5 | N5: =L5-M5 | O5: =IFERROR(N5/L5, 0) | P5: =YEAR(C5) | Q5: =TEXT(C5, "yyyy-mm") | R5: Mobile App | S5: REG-LATAM
A6: DTL-0000002 | B6: ORD-000002 | C6: 2023-09-25 | D6: CUST-03511 | E6: PRD-0203 | F6: 3 | G6: =IFERROR(XLOOKUP(E6, '04_Products'!$A:$A, '04_Products'!$G:$G), 991.36) | H6: =IFERROR(XLOOKUP(E6, '04_Products'!$A:$A, '04_Products'!$F:$F), 0) | I6: =F6*G6 | J6: 0.05 | K6: =I6*J6 | L6: =I6-K6 | M6: =F6*H6 | N6: =L6-M6 | O6: =IFERROR(N6/L6, 0) | P6: =YEAR(C6) | Q6: =TEXT(C6, "yyyy-mm") | R6: Mobile App | S6: REG-APAC
A7: DTL-0000003 | B7: ORD-000003 | C7: 2025-08-03 | D7: CUST-00043 | E7: PRD-0360 | F7: 2 | G7: =IFERROR(XLOOKUP(E7, '04_Products'!$A:$A, '04_Products'!$G:$G), 465.92) | H7: =IFERROR(XLOOKUP(E7, '04_Products'!$A:$A, '04_Products'!$F:$F), 0) | I7: =F7*G7 | J7: 0 | K7: =I7*J7 | L7: =I7-K7 | M7: =F7*H7 | N7: =L7-M7 | O7: =IFERROR(N7/L7, 0) | P7: =YEAR(C7) | Q7: =TEXT(C7, "yyyy-mm") | R7: B2B Portal | S7: REG-NA
A8: DTL-0000004 | B8: ORD-000003 | C8: 2025-08-03 | D8: CUST-00043 | E8: PRD-0429 | F8: 1 | G8: =IFERROR(XLOOKUP(E8, '04_Products'!$A:$A, '04_Products'!$G:$G), 790.21) | H8: =IFERROR(XLOOKUP(E8, '04_Products'!$A:$A, '04_Products'!$F:$F), 0) | I8: =F8*G8 | J8: 0.1 | K8: =I8*J8 | L8: =I8-K8 | M8: =F8*H8 | N8: =L8-M8 | O8: =IFERROR(N8/L8, 0) | P8: =YEAR(C8) | Q8: =TEXT(C8, "yyyy-mm") | R8: B2B Portal | S8: REG-NA
A9: DTL-0000005 | B9: ORD-000003 | C9: 2025-08-03 | D9: CUST-00043 | E9: PRD-0166 | F9: 2 | G9: =IFERROR(XLOOKUP(E9, '04_Products'!$A:$A, '04_Products'!$G:$G), 173.50) | H9: =IFERROR(XLOOKUP(E9, '04_Products'!$A:$A, '04_Products'!$F:$F), 0) | I9: =F9*G9 | J9: 0.1 | K9: =I9*J9 | L9: =I9-K9 | M9: =F9*H9 | N9: =L9-M9 | O9: =IFERROR(N9/L9, 0) | P9: =YEAR(C9) | Q9: =TEXT(C9, "yyyy-mm") | R9: B2B Portal | S9: REG-NA
A10: DTL-0000006 | B10: ORD-000003 | C10: 2025-08-03 | D10: CUST-00043 | E10: PRD-0317 | F10: 1 | G10: =IFERROR(XLOOKUP(E10, '04_Products'!$A:$A, '04_Products'!$G:$G), 484.56) | H10: =IFERROR(XLOOKUP(E10, '04_Products'!$A:$A, '04_Products'!$F:$F), 0) | I10: =F10*G10 | J10: 0 | K10: =I10*J10 | L10: =I10-K10 | M10: =F10*H10 | N10: =L10-M10 | O10: =IFERROR(N10/L10, 0) | P10: =YEAR(C10) | Q10: =TEXT(C10, "yyyy-mm") | R10: B2B Portal | S10: REG-NA
A11: DTL-0000007 | B11: ORD-000003 | C11: 2025-08-03 | D11: CUST-00043 | E11: PRD-0249 | F11: 1 | G11: =IFERROR(XLOOKUP(E11, '04_Products'!$A:$A, '04_Products'!$G:$G), 69.32) | H11: =IFERROR(XLOOKUP(E11, '04_Products'!$A:$A, '04_Products'!$F:$F), 0) | I11: =F11*G11 | J11: 0.1 | K11: =I11*J11 | L11: =I11-K11 | M11: =F11*H11 | N11: =L11-M11 | O11: =IFERROR(N11/L11, 0) | P11: =YEAR(C11) | Q11: =TEXT(C11, "yyyy-mm") | R11: B2B Portal | S11: REG-NA
A12: DTL-0000008 | B12: ORD-000004 | C12: 2025-03-04 | D12: CUST-03363 | E12: PRD-0141 | F12: 3 | G12: =IFERROR(XLOOKUP(E12, '04_Products'!$A:$A, '04_Products'!$G:$G), 53.70) | H12: =IFERROR(XLOOKUP(E12, '04_Products'!$A:$A, '04_Products'!$F:$F), 0) | I12: =F12*G12 | J12: 0 | K12: =I12*J12 | L12: =I12-K12 | M12: =F12*H12 | N12: =L12-M12 | O12: =IFERROR(N12/L12, 0) | P12: =YEAR(C12) | Q12: =TEXT(C12, "yyyy-mm") | R12: Direct Web | S12: REG-APAC
A13: DTL-0000009 | B13: ORD-000004 | C13: 2025-03-04 | D13: CUST-03363 | E13: PRD-0388 | F13: 1 | G13: =IFERROR(XLOOKUP(E13, '04_Products'!$A:$A, '04_Products'!$G:$G), 318.52) | H13: =IFERROR(XLOOKUP(E13, '04_Products'!$A:$A, '04_Products'!$F:$F), 0) | I13: =F13*G13 | J13: 0 | K13: =I13*J13 | L13: =I13-K13 | M13: =F13*H13 | N13: =L13-M13 | O13: =IFERROR(N13/L13, 0) | P13: =YEAR(C13) | Q13: =TEXT(C13, "yyyy-mm") | R13: Direct Web | S13: REG-APAC
A14: DTL-0000010 | B14: ORD-000004 | C14: 2025-03-04 | D14: CUST-03363 | E14: PRD-0301 | F14: 1 | G14: =IFERROR(XLOOKUP(E14, '04_Products'!$A:$A, '04_Products'!$G:$G), 528.29) | H14: =IFERROR(XLOOKUP(E14, '04_Products'!$A:$A, '04_Products'!$F:$F), 0) | I14: =F14*G14 | J14: 0.15 | K14: =I14*J14 | L14: =I14-K14 | M14: =F14*H14 | N14: =L14-M14 | O14: =IFERROR(N14/L14, 0) | P14: =YEAR(C14) | Q14: =TEXT(C14, "yyyy-mm") | R14: Direct Web | S14: REG-APAC
A15: DTL-0000011 | B15: ORD-000004 | C15: 2025-03-04 | D15: CUST-03363 | E15: PRD-0399 | F15: 2 | G15: =IFERROR(XLOOKUP(E15, '04_Products'!$A:$A, '04_Products'!$G:$G), 933.08) | H15: =IFERROR(XLOOKUP(E15, '04_Products'!$A:$A, '04_Products'!$F:$F), 0) | I15: =F15*G15 | J15: 0.05 | K15: =I15*J15 | L15: =I15-K15 | M15: =F15*H15 | N15: =L15-M15 | O15: =IFERROR(N15/L15, 0) | P15: =YEAR(C15) | Q15: =TEXT(C15, "yyyy-mm") | R15: Direct Web | S15: REG-APAC
A16: DTL-0000012 | B16: ORD-000005 | C16: 2023-09-26 | D16: CUST-01966 | E16: PRD-0248 | F16: 2 | G16: =IFERROR(XLOOKUP(E16, '04_Products'!$A:$A, '04_Products'!$G:$G), 603.58) | H16: =IFERROR(XLOOKUP(E16, '04_Products'!$A:$A, '04_Products'!$F:$F), 0) | I16: =F16*G16 | J16: 0.05 | K16: =I16*J16 | L16: =I16-K16 | M16: =F16*H16 | N16: =L16-M16 | O16: =IFERROR(N16/L16, 0) | P16: =YEAR(C16) | Q16: =TEXT(C16, "yyyy-mm") | R16: Direct Web | S16: REG-NA
A17: DTL-0000013 | B17: ORD-000005 | C17: 2023-09-26 | D17: CUST-01966 | E17: PRD-0215 | F17: 1 | G17: =IFERROR(XLOOKUP(E17, '04_Products'!$A:$A, '04_Products'!$G:$G), 1006.33) | H17: =IFERROR(XLOOKUP(E17, '04_Products'!$A:$A, '04_Products'!$F:$F), 0) | I17: =F17*G17 | J17: 0.2 | K17: =I17*J17 | L17: =I17-K17 | M17: =F17*H17 | N17: =L17-M17 | O17: =IFERROR(N17/L17, 0) | P17: =YEAR(C17) | Q17: =TEXT(C17, "yyyy-mm") | R17: Direct Web | S17: REG-NA
A18: DTL-0000014 | B18: ORD-000006 | C18: 2023-01-19 | D18: CUST-07581 | E18: PRD-0019 | F18: 1 | G18: =IFERROR(XLOOKUP(E18, '04_Products'!$A:$A, '04_Products'!$G:$G), 444.46) | H18: =IFERROR(XLOOKUP(E18, '04_Products'!$A:$A, '04_Products'!$F:$F), 0) | I18: =F18*G18 | J18: 0.15 | K18: =I18*J18 | L18: =I18-K18 | M18: =F18*H18 | N18: =L18-M18 | O18: =IFERROR(N18/L18, 0) | P18: =YEAR(C18) | Q18: =TEXT(C18, "yyyy-mm") | R18: Direct Web | S18: REG-NA
A19: DTL-0000015 | B19: ORD-000006 | C19: 2023-01-19 | D19: CUST-07581 | E19: PRD-0359 | F19: 1 | G19: =IFERROR(XLOOKUP(E19, '04_Products'!$A:$A, '04_Products'!$G:$G), 1075.75) | H19: =IFERROR(XLOOKUP(E19, '04_Products'!$A:$A, '04_Products'!$F:$F), 0) | I19: =F19*G19 | J19: 0 | K19: =I19*J19 | L19: =I19-K19 | M19: =F19*H19 | N19: =L19-M19 | O19: =IFERROR(N19/L19, 0) | P19: =YEAR(C19) | Q19: =TEXT(C19, "yyyy-mm") | R19: Direct Web | S19: REG-NA
A20: DTL-0000016 | B20: ORD-000006 | C20: 2023-01-19 | D20: CUST-07581 | E20: PRD-0385 | F20: 1 | G20: =IFERROR(XLOOKUP(E20, '04_Products'!$A:$A, '04_Products'!$G:$G), 209.78) | H20: =IFERROR(XLOOKUP(E20, '04_Products'!$A:$A, '04_Products'!$F:$F), 0) | I20: =F20*G20 | J20: 0 | K20: =I20*J20 | L20: =I20-K20 | M20: =F20*H20 | N20: =L20-M20 | O20: =IFERROR(N20/L20, 0) | P20: =YEAR(C20) | Q20: =TEXT(C20, "yyyy-mm") | R20: Direct Web | S20: REG-NA
A21: DTL-0000017 | B21: ORD-000006 | C21: 2023-01-19 | D21: CUST-07581 | E21: PRD-0208 | F21: 1 | G21: =IFERROR(XLOOKUP(E21, '04_Products'!$A:$A, '04_Products'!$G:$G), 47.15) | H21: =IFERROR(XLOOKUP(E21, '04_Products'!$A:$A, '04_Products'!$F:$F), 0) | I21: =F21*G21 | J21: 0 | K21: =I21*J21 | L21: =I21-K21 | M21: =F21*H21 | N21: =L21-M21 | O21: =IFERROR(N21/L21, 0) | P21: =YEAR(C21) | Q21: =TEXT(C21, "yyyy-mm") | R21: Direct Web | S21: REG-NA
A22: DTL-0000018 | B22: ORD-000007 | C22: 2024-03-09 | D22: CUST-00360 | E22: PRD-0222 | F22: 8 | G22: =IFERROR(XLOOKUP(E22, '04_Products'!$A:$A, '04_Products'!$G:$G), 748.03) | H22: =IFERROR(XLOOKUP(E22, '04_Products'!$A:$A, '04_Products'!$F:$F), 0) | I22: =F22*G22 | J22: 0 | K22: =I22*J22 | L22: =I22-K22 | M22: =F22*H22 | N22: =L22-M22 | O22: =IFERROR(N22/L22, 0) | P22: =YEAR(C22) | Q22: =TEXT(C22, "yyyy-mm") | R22: Direct Web | S22: REG-APAC
A23: DTL-0000019 | B23: ORD-000008 | C23: 2025-11-23 | D23: CUST-05897 | E23: PRD-0141 | F23: 1 | G23: =IFERROR(XLOOKUP(E23, '04_Products'!$A:$A, '04_Products'!$G:$G), 53.70) | H23: =IFERROR(XLOOKUP(E23, '04_Products'!$A:$A, '04_Products'!$F:$F), 0) | I23: =F23*G23 | J23: 0 | K23: =I23*J23 | L23: =I23-K23 | M23: =F23*H23 | N23: =L23-M23 | O23: =IFERROR(N23/L23, 0) | P23: =YEAR(C23) | Q23: =TEXT(C23, "yyyy-mm") | R23: Direct Web | S23: REG-APAC
A24: DTL-0000020 | B24: ORD-000008 | C24: 2025-11-23 | D24: CUST-05897 | E24: PRD-0143 | F24: 3 | G24: =IFERROR(XLOOKUP(E24, '04_Products'!$A:$A, '04_Products'!$G:$G), 359.58) | H24: =IFERROR(XLOOKUP(E24, '04_Products'!$A:$A, '04_Products'!$F:$F), 0) | I24: =F24*G24 | J24: 0 | K24: =I24*J24 | L24: =I24-K24 | M24: =F24*H24 | N24: =L24-M24 | O24: =IFERROR(N24/L24, 0) | P24: =YEAR(C24) | Q24: =TEXT(C24, "yyyy-mm") | R24: Direct Web | S24: REG-APAC
A25: DTL-0000021 | B25: ORD-000008 | C25: 2025-11-23 | D25: CUST-05897 | E25: PRD-0281 | F25: 1 | G25: =IFERROR(XLOOKUP(E25, '04_Products'!$A:$A, '04_Products'!$G:$G), 19.01) | H25: =IFERROR(XLOOKUP(E25, '04_Products'!$A:$A, '04_Products'!$F:$F), 0) | I25: =F25*G25 | J25: 0.15 | K25: =I25*J25 | L25: =I25-K25 | M25: =F25*H25 | N25: =L25-M25 | O25: =IFERROR(N25/L25, 0) | P25: =YEAR(C25) | Q25: =TEXT(C25, "yyyy-mm") | R25: Direct Web | S25: REG-APAC
A26: DTL-0000022 | B26: ORD-000009 | C26: 2024-12-20 | D26: CUST-05907 | E26: PRD-0236 | F26: 2 | G26: =IFERROR(XLOOKUP(E26, '04_Products'!$A:$A, '04_Products'!$G:$G), 128.74) | H26: =IFERROR(XLOOKUP(E26, '04_Products'!$A:$A, '04_Products'!$F:$F), 0) | I26: =F26*G26 | J26: 0 | K26: =I26*J26 | L26: =I26-K26 | M26: =F26*H26 | N26: =L26-M26 | O26: =IFERROR(N26/L26, 0) | P26: =YEAR(C26) | Q26: =TEXT(C26, "yyyy-mm") | R26: Mobile App | S26: REG-EU
A27: DTL-0000023 | B27: ORD-000010 | C27: 2024-01-17 | D27: CUST-00188 | E27: PRD-0035 | F27: 1 | G27: =IFERROR(XLOOKUP(E27, '04_Products'!$A:$A, '04_Products'!$G:$G), 584.68) | H27: =IFERROR(XLOOKUP(E27, '04_Products'!$A:$A, '04_Products'!$F:$F), 0) | I27: =F27*G27 | J27: 0.2 | K27: =I27*J27 | L27: =I27-K27 | M27: =F27*H27 | N27: =L27-M27 | O27: =IFERROR(N27/L27, 0) | P27: =YEAR(C27) | Q27: =TEXT(C27, "yyyy-mm") | R27: Direct Web | S27: REG-LATAM
A28: DTL-0000024 | B28: ORD-000011 | C28: 2025-07-28 | D28: CUST-00289 | E28: PRD-0226 | F28: 2 | G28: =IFERROR(XLOOKUP(E28, '04_Products'!$A:$A, '04_Products'!$G:$G), 849.36) | H28: =IFERROR(XLOOKUP(E28, '04_Products'!$A:$A, '04_Products'!$F:$F), 0) | I28: =F28*G28 | J28: 0.15 | K28: =I28*J28 | L28: =I28-K28 | M28: =F28*H28 | N28: =L28-M28 | O28: =IFERROR(N28/L28, 0) | P28: =YEAR(C28) | Q28: =TEXT(C28, "yyyy-mm") | R28: Affiliate Partner | S28: REG-LATAM
A29: DTL-0000025 | B29: ORD-000011 | C29: 2025-07-28 | D29: CUST-00289 | E29: PRD-0256 | F29: 1 | G29: =IFERROR(XLOOKUP(E29, '04_Products'!$A:$A, '04_Products'!$G:$G), 235.18) | H29: =IFERROR(XLOOKUP(E29, '04_Products'!$A:$A, '04_Products'!$F:$F), 0) | I29: =F29*G29 | J29: 0 | K29: =I29*J29 | L29: =I29-K29 | M29: =F29*H29 | N29: =L29-M29 | O29: =IFERROR(N29/L29, 0) | P29: =YEAR(C29) | Q29: =TEXT(C29, "yyyy-mm") | R29: Affiliate Partner | S29: REG-LATAM
A30: DTL-0000026 | B30: ORD-000011 | C30: 2025-07-28 | D30: CUST-00289 | E30: PRD-0257 | F30: 2 | G30: =IFERROR(XLOOKUP(E30, '04_Products'!$A:$A, '04_Products'!$G:$G), 31.28) | H30: =IFERROR(XLOOKUP(E30, '04_Products'!$A:$A, '04_Products'!$F:$F), 0) | I30: =F30*G30 | J30: 0.05 | K30: =I30*J30 | L30: =I30-K30 | M30: =F30*H30 | N30: =L30-M30 | O30: =IFERROR(N30/L30, 0) | P30: =YEAR(C30) | Q30: =TEXT(C30, "yyyy-mm") | R30: Affiliate Partner | S30: REG-LATAM
A31: DTL-0000027 | B31: ORD-000012 | C31: 2025-05-31 | D31: CUST-06135 | E31: PRD-0225 | F31: 1 | G31: =IFERROR(XLOOKUP(E31, '04_Products'!$A:$A, '04_Products'!$G:$G), 266.58) | H31: =IFERROR(XLOOKUP(E31, '04_Products'!$A:$A, '04_Products'!$F:$F), 0) | I31: =F31*G31 | J31: 0.3 | K31: =I31*J31 | L31: =I31-K31 | M31: =F31*H31 | N31: =L31-M31 | O31: =IFERROR(N31/L31, 0) | P31: =YEAR(C31) | Q31: =TEXT(C31, "yyyy-mm") | R31: Affiliate Partner | S31: REG-EU
A32: DTL-0000028 | B32: ORD-000013 | C32: 2023-08-10 | D32: CUST-03549 | E32: PRD-0210 | F32: 1 | G32: =IFERROR(XLOOKUP(E32, '04_Products'!$A:$A, '04_Products'!$G:$G), 920.55) | H32: =IFERROR(XLOOKUP(E32, '04_Products'!$A:$A, '04_Products'!$F:$F), 0) | I32: =F32*G32 | J32: 0.1 | K32: =I32*J32 | L32: =I32-K32 | M32: =F32*H32 | N32: =L32-M32 | O32: =IFERROR(N32/L32, 0) | P32: =YEAR(C32) | Q32: =TEXT(C32, "yyyy-mm") | R32: Direct Web | S32: REG-APAC
A33: DTL-0000029 | B33: ORD-000013 | C33: 2023-08-10 | D33: CUST-03549 | E33: PRD-0374 | F33: 3 | G33: =IFERROR(XLOOKUP(E33, '04_Products'!$A:$A, '04_Products'!$G:$G), 549.09) | H33: =IFERROR(XLOOKUP(E33, '04_Products'!$A:$A, '04_Products'!$F:$F), 0) | I33: =F33*G33 | J33: 0 | K33: =I33*J33 | L33: =I33-K33 | M33: =F33*H33 | N33: =L33-M33 | O33: =IFERROR(N33/L33, 0) | P33: =YEAR(C33) | Q33: =TEXT(C33, "yyyy-mm") | R33: Direct Web | S33: REG-APAC
A34: DTL-0000030 | B34: ORD-000013 | C34: 2023-08-10 | D34: CUST-03549 | E34: PRD-0361 | F34: 1 | G34: =IFERROR(XLOOKUP(E34, '04_Products'!$A:$A, '04_Products'!$G:$G), 13.14) | H34: =IFERROR(XLOOKUP(E34, '04_Products'!$A:$A, '04_Products'!$F:$F), 0) | I34: =F34*G34 | J34: 0 | K34: =I34*J34 | L34: =I34-K34 | M34: =F34*H34 | N34: =L34-M34 | O34: =IFERROR(N34/L34, 0) | P34: =YEAR(C34) | Q34: =TEXT(C34, "yyyy-mm") | R34: Direct Web | S34: REG-APAC
A35: DTL-0000031 | B35: ORD-000013 | C35: 2023-08-10 | D35: CUST-03549 | E35: PRD-0415 | F35: 1 | G35: =IFERROR(XLOOKUP(E35, '04_Products'!$A:$A, '04_Products'!$G:$G), 934.21) | H35: =IFERROR(XLOOKUP(E35, '04_Products'!$A:$A, '04_Products'!$F:$F), 0) | I35: =F35*G35 | J35: 0 | K35: =I35*J35 | L35: =I35-K35 | M35: =F35*H35 | N35: =L35-M35 | O35: =IFERROR(N35/L35, 0) | P35: =YEAR(C35) | Q35: =TEXT(C35, "yyyy-mm") | R35: Direct Web | S35: REG-APAC
A36: DTL-0000033 | B36: ORD-000015 | C36: 2024-09-16 | D36: CUST-05715 | E36: PRD-0108 | F36: 1 | G36: =IFERROR(XLOOKUP(E36, '04_Products'!$A:$A, '04_Products'!$G:$G), 217.90) | H36: =IFERROR(XLOOKUP(E36, '04_Products'!$A:$A, '04_Products'!$F:$F), 0) | I36: =F36*G36 | J36: 0.1 | K36: =I36*J36 | L36: =I36-K36 | M36: =F36*H36 | N36: =L36-M36 | O36: =IFERROR(N36/L36, 0) | P36: =YEAR(C36) | Q36: =TEXT(C36, "yyyy-mm") | R36: Direct Web | S36: REG-NA
A37: DTL-0000034 | B37: ORD-000015 | C37: 2024-09-16 | D37: CUST-05715 | E37: PRD-0191 | F37: 1 | G37: =IFERROR(XLOOKUP(E37, '04_Products'!$A:$A, '04_Products'!$G:$G), 45.09) | H37: =IFERROR(XLOOKUP(E37, '04_Products'!$A:$A, '04_Products'!$F:$F), 0) | I37: =F37*G37 | J37: 0 | K37: =I37*J37 | L37: =I37-K37 | M37: =F37*H37 | N37: =L37-M37 | O37: =IFERROR(N37/L37, 0) | P37: =YEAR(C37) | Q37: =TEXT(C37, "yyyy-mm") | R37: Direct Web | S37: REG-NA
A38: DTL-0000035 | B38: ORD-000016 | C38: 2023-08-12 | D38: CUST-03436 | E38: PRD-0026 | F38: 1 | G38: =IFERROR(XLOOKUP(E38, '04_Products'!$A:$A, '04_Products'!$G:$G), 469.49) | H38: =IFERROR(XLOOKUP(E38, '04_Products'!$A:$A, '04_Products'!$F:$F), 0) | I38: =F38*G38 | J38: 0 | K38: =I38*J38 | L38: =I38-K38 | M38: =F38*H38 | N38: =L38-M38 | O38: =IFERROR(N38/L38, 0) | P38: =YEAR(C38) | Q38: =TEXT(C38, "yyyy-mm") | R38: Direct Web | S38: REG-EU
A39: DTL-0000036 | B39: ORD-000017 | C39: 2025-02-19 | D39: CUST-05569 | E39: PRD-0094 | F39: 1 | G39: =IFERROR(XLOOKUP(E39, '04_Products'!$A:$A, '04_Products'!$G:$G), 282.30) | H39: =IFERROR(XLOOKUP(E39, '04_Products'!$A:$A, '04_Products'!$F:$F), 0) | I39: =F39*G39 | J39: 0.1 | K39: =I39*J39 | L39: =I39-K39 | M39: =F39*H39 | N39: =L39-M39 | O39: =IFERROR(N39/L39, 0) | P39: =YEAR(C39) | Q39: =TEXT(C39, "yyyy-mm") | R39: Mobile App | S39: REG-NA
A40: DTL-0000037 | B40: ORD-000018 | C40: 2023-11-05 | D40: CUST-01039 | E40: PRD-0254 | F40: 3 | G40: =IFERROR(XLOOKUP(E40, '04_Products'!$A:$A, '04_Products'!$G:$G), 219.63) | H40: =IFERROR(XLOOKUP(E40, '04_Products'!$A:$A, '04_Products'!$F:$F), 0) | I40: =F40*G40 | J40: 0 | K40: =I40*J40 | L40: =I40-K40 | M40: =F40*H40 | N40: =L40-M40 | O40: =IFERROR(N40/L40, 0) | P40: =YEAR(C40) | Q40: =TEXT(C40, "yyyy-mm") | R40: Direct Web | S40: REG-NA
A41: DTL-0000038 | B41: ORD-000019 | C41: 2024-11-10 | D41: CUST-01504 | E41: PRD-0417 | F41: 1 | G41: =IFERROR(XLOOKUP(E41, '04_Products'!$A:$A, '04_Products'!$G:$G), 134.04) | H41: =IFERROR(XLOOKUP(E41, '04_Products'!$A:$A, '04_Products'!$F:$F), 0) | I41: =F41*G41 | J41: 0.3 | K41: =I41*J41 | L41: =I41-K41 | M41: =F41*H41 | N41: =L41-M41 | O41: =IFERROR(N41/L41, 0) | P41: =YEAR(C41) | Q41: =TEXT(C41, "yyyy-mm") | R41: Direct Web | S41: REG-NA
A42: DTL-0000039 | B42: ORD-000019 | C42: 2024-11-10 | D42: CUST-01504 | E42: PRD-0163 | F42: 3 | G42: =IFERROR(XLOOKUP(E42, '04_Products'!$A:$A, '04_Products'!$G:$G), 101.40) | H42: =IFERROR(XLOOKUP(E42, '04_Products'!$A:$A, '04_Products'!$F:$F), 0) | I42: =F42*G42 | J42: 0 | K42: =I42*J42 | L42: =I42-K42 | M42: =F42*H42 | N42: =L42-M42 | O42: =IFERROR(N42/L42, 0) | P42: =YEAR(C42) | Q42: =TEXT(C42, "yyyy-mm") | R42: Direct Web | S42: REG-NA
A43: DTL-0000040 | B43: ORD-000019 | C43: 2024-11-10 | D43: CUST-01504 | E43: PRD-0154 | F43: 3 | G43: =IFERROR(XLOOKUP(E43, '04_Products'!$A:$A, '04_Products'!$G:$G), 168.94) | H43: =IFERROR(XLOOKUP(E43, '04_Products'!$A:$A, '04_Products'!$F:$F), 0) | I43: =F43*G43 | J43: 0 | K43: =I43*J43 | L43: =I43-K43 | M43: =F43*H43 | N43: =L43-M43 | O43: =IFERROR(N43/L43, 0) | P43: =YEAR(C43) | Q43: =TEXT(C43, "yyyy-mm") | R43: Direct Web | S43: REG-NA
A44: DTL-0000041 | B44: ORD-000020 | C44: 2024-03-18 | D44: CUST-07544 | E44: PRD-0184 | F44: 1 | G44: =IFERROR(XLOOKUP(E44, '04_Products'!$A:$A, '04_Products'!$G:$G), 79.57) | H44: =IFERROR(XLOOKUP(E44, '04_Products'!$A:$A, '04_Products'!$F:$F), 0) | I44: =F44*G44 | J44: 0.3 | K44: =I44*J44 | L44: =I44-K44 | M44: =F44*H44 | N44: =L44-M44 | O44: =IFERROR(N44/L44, 0) | P44: =YEAR(C44) | Q44: =TEXT(C44, "yyyy-mm") | R44: Mobile App | S44: REG-EU
A45: DTL-0000042 | B45: ORD-000021 | C45: 2024-10-17 | D45: CUST-00428 | E45: PRD-0336 | F45: 3 | G45: =IFERROR(XLOOKUP(E45, '04_Products'!$A:$A, '04_Products'!$G:$G), 216.76) | H45: =IFERROR(XLOOKUP(E45, '04_Products'!$A:$A, '04_Products'!$F:$F), 0) | I45: =F45*G45 | J45: 0.1 | K45: =I45*J45 | L45: =I45-K45 | M45: =F45*H45 | N45: =L45-M45 | O45: =IFERROR(N45/L45, 0) | P45: =YEAR(C45) | Q45: =TEXT(C45, "yyyy-mm") | R45: B2B Portal | S45: REG-APAC
A46: DTL-0000043 | B46: ORD-000022 | C46: 2025-03-29 | D46: CUST-05119 | E46: PRD-0131 | F46: 1 | G46: =IFERROR(XLOOKUP(E46, '04_Products'!$A:$A, '04_Products'!$G:$G), 66.07) | H46: =IFERROR(XLOOKUP(E46, '04_Products'!$A:$A, '04_Products'!$F:$F), 0) | I46: =F46*G46 | J46: 0.1 | K46: =I46*J46 | L46: =I46-K46 | M46: =F46*H46 | N46: =L46-M46 | O46: =IFERROR(N46/L46, 0) | P46: =YEAR(C46) | Q46: =TEXT(C46, "yyyy-mm") | R46: Direct Web | S46: REG-APAC
A47: DTL-0000044 | B47: ORD-000023 | C47: 2025-02-12 | D47: CUST-06053 | E47: PRD-0342 | F47: 1 | G47: =IFERROR(XLOOKUP(E47, '04_Products'!$A:$A, '04_Products'!$G:$G), 994.42) | H47: =IFERROR(XLOOKUP(E47, '04_Products'!$A:$A, '04_Products'!$F:$F), 0) | I47: =F47*G47 | J47: 0 | K47: =I47*J47 | L47: =I47-K47 | M47: =F47*H47 | N47: =L47-M47 | O47: =IFERROR(N47/L47, 0) | P47: =YEAR(C47) | Q47: =TEXT(C47, "yyyy-mm") | R47: Mobile App | S47: REG-NA
A48: DTL-0000045 | B48: ORD-000024 | C48: 2023-11-14 | D48: CUST-06698 | E48: PRD-0321 | F48: 2 | G48: =IFERROR(XLOOKUP(E48, '04_Products'!$A:$A, '04_Products'!$G:$G), 684.87) | H48: =IFERROR(XLOOKUP(E48, '04_Products'!$A:$A, '04_Products'!$F:$F), 0) | I48: =F48*G48 | J48: 0.1 | K48: =I48*J48 | L48: =I48-K48 | M48: =F48*H48 | N48: =L48-M48 | O48: =IFERROR(N48/L48, 0) | P48: =YEAR(C48) | Q48: =TEXT(C48, "yyyy-mm") | R48: Affiliate Partner | S48: REG-EU
A49: DTL-0000046 | B49: ORD-000024 | C49: 2023-11-14 | D49: CUST-06698 | E49: PRD-0259 | F49: 4 | G49: =IFERROR(XLOOKUP(E49, '04_Products'!$A:$A, '04_Products'!$G:$G), 427.15) | H49: =IFERROR(XLOOKUP(E49, '04_Products'!$A:$A, '04_Products'!$F:$F), 0) | I49: =F49*G49 | J49: 0 | K49: =I49*J49 | L49: =I49-K49 | M49: =F49*H49 | N49: =L49-M49 | O49: =IFERROR(N49/L49, 0) | P49: =YEAR(C49) | Q49: =TEXT(C49, "yyyy-mm") | R49: Affiliate Partner | S49: REG-EU
A50: DTL-0000047 | B50: ORD-000024 | C50: 2023-11-14 | D50: CUST-06698 | E50: PRD-0268 | F50: 2 | G50: =IFERROR(XLOOKUP(E50, '04_Products'!$A:$A, '04_Products'!$G:$G), 69.90) | H50: =IFERROR(XLOOKUP(E50, '04_Products'!$A:$A, '04_Products'!$F:$F), 0) | I50: =F50*G50 | J50: 0 | K50: =I50*J50 | L50: =I50-K50 | M50: =F50*H50 | N50: =L50-M50 | O50: =IFERROR(N50/L50, 0) | P50: =YEAR(C50) | Q50: =TEXT(C50, "yyyy-mm") | R50: Affiliate Partner | S50: REG-EU
A51: DTL-0000048 | B51: ORD-000025 | C51: 2025-10-22 | D51: CUST-02242 | E51: PRD-0079 | F51: 3 | G51: =IFERROR(XLOOKUP(E51, '04_Products'!$A:$A, '04_Products'!$G:$G), 1234.41) | H51: =IFERROR(XLOOKUP(E51, '04_Products'!$A:$A, '04_Products'!$F:$F), 0) | I51: =F51*G51 | J51: 0.15 | K51: =I51*J51 | L51: =I51-K51 | M51: =F51*H51 | N51: =L51-M51 | O51: =IFERROR(N51/L51, 0) | P51: =YEAR(C51) | Q51: =TEXT(C51, "yyyy-mm") | R51: Direct Web | S51: REG-NA
A52: DTL-0000049 | B52: ORD-000025 | C52: 2025-10-22 | D52: CUST-02242 | E52: PRD-0470 | F52: 3 | G52: =IFERROR(XLOOKUP(E52, '04_Products'!$A:$A, '04_Products'!$G:$G), 1097.57) | H52: =IFERROR(XLOOKUP(E52, '04_Products'!$A:$A, '04_Products'!$F:$F), 0) | I52: =F52*G52 | J52: 0.1 | K52: =I52*J52 | L52: =I52-K52 | M52: =F52*H52 | N52: =L52-M52 | O52: =IFERROR(N52/L52, 0) | P52: =YEAR(C52) | Q52: =TEXT(C52, "yyyy-mm") | R52: Direct Web | S52: REG-NA
A53: DTL-0000050 | B53: ORD-000026 | C53: 2024-12-30 | D53: CUST-03439 | E53: PRD-0257 | F53: 2 | G53: =IFERROR(XLOOKUP(E53, '04_Products'!$A:$A, '04_Products'!$G:$G), 31.28) | H53: =IFERROR(XLOOKUP(E53, '04_Products'!$A:$A, '04_Products'!$F:$F), 0) | I53: =F53*G53 | J53: 0 | K53: =I53*J53 | L53: =I53-K53 | M53: =F53*H53 | N53: =L53-M53 | O53: =IFERROR(N53/L53, 0) | P53: =YEAR(C53) | Q53: =TEXT(C53, "yyyy-mm") | R53: Direct Web | S53: REG-NA
A54: DTL-0000051 | B54: ORD-000027 | C54: 2024-08-17 | D54: CUST-05208 | E54: PRD-0314 | F54: 2 | G54: =IFERROR(XLOOKUP(E54, '04_Products'!$A:$A, '04_Products'!$G:$G), 28.50) | H54: =IFERROR(XLOOKUP(E54, '04_Products'!$A:$A, '04_Products'!$F:$F), 0) | I54: =F54*G54 | J54: 0.3 | K54: =I54*J54 | L54: =I54-K54 | M54: =F54*H54 | N54: =L54-M54 | O54: =IFERROR(N54/L54, 0) | P54: =YEAR(C54) | Q54: =TEXT(C54, "yyyy-mm") | R54: Direct Web | S54: REG-APAC
A55: DTL-0000052 | B55: ORD-000028 | C55: 2025-07-14 | D55: CUST-02394 | E55: PRD-0433 | F55: 1 | G55: =IFERROR(XLOOKUP(E55, '04_Products'!$A:$A, '04_Products'!$G:$G), 545.86) | H55: =IFERROR(XLOOKUP(E55, '04_Products'!$A:$A, '04_Products'!$F:$F), 0) | I55: =F55*G55 | J55: 0.1 | K55: =I55*J55 | L55: =I55-K55 | M55: =F55*H55 | N55: =L55-M55 | O55: =IFERROR(N55/L55, 0) | P55: =YEAR(C55) | Q55: =TEXT(C55, "yyyy-mm") | R55: Mobile App | S55: REG-APAC
A56: DTL-0000053 | B56: ORD-000028 | C56: 2025-07-14 | D56: CUST-02394 | E56: PRD-0132 | F56: 1 | G56: =IFERROR(XLOOKUP(E56, '04_Products'!$A:$A, '04_Products'!$G:$G), 792.09) | H56: =IFERROR(XLOOKUP(E56, '04_Products'!$A:$A, '04_Products'!$F:$F), 0) | I56: =F56*G56 | J56: 0.25 | K56: =I56*J56 | L56: =I56-K56 | M56: =F56*H56 | N56: =L56-M56 | O56: =IFERROR(N56/L56, 0) | P56: =YEAR(C56) | Q56: =TEXT(C56, "yyyy-mm") | R56: Mobile App | S56: REG-APAC
A57: DTL-0000054 | B57: ORD-000029 | C57: 2024-10-17 | D57: CUST-07775 | E57: PRD-0410 | F57: 2 | G57: =IFERROR(XLOOKUP(E57, '04_Products'!$A:$A, '04_Products'!$G:$G), 13.14) | H57: =IFERROR(XLOOKUP(E57, '04_Products'!$A:$A, '04_Products'!$F:$F), 0) | I57: =F57*G57 | J57: 0 | K57: =I57*J57 | L57: =I57-K57 | M57: =F57*H57 | N57: =L57-M57 | O57: =IFERROR(N57/L57, 0) | P57: =YEAR(C57) | Q57: =TEXT(C57, "yyyy-mm") | R57: Mobile App | S57: REG-LATAM
A58: DTL-0000055 | B58: ORD-000030 | C58: 2023-05-09 | D58: CUST-00164 | E58: PRD-0048 | F58: 1 | G58: =IFERROR(XLOOKUP(E58, '04_Products'!$A:$A, '04_Products'!$G:$G), 39.00) | H58: =IFERROR(XLOOKUP(E58, '04_Products'!$A:$A, '04_Products'!$F:$F), 0) | I58: =F58*G58 | J58: 0 | K58: =I58*J58 | L58: =I58-K58 | M58: =F58*H58 | N58: =L58-M58 | O58: =IFERROR(N58/L58, 0) | P58: =YEAR(C58) | Q58: =TEXT(C58, "yyyy-mm") | R58: Mobile App | S58: REG-NA
A59: DTL-0000056 | B59: ORD-000030 | C59: 2023-05-09 | D59: CUST-00164 | E59: PRD-0004 | F59: 1 | G59: =IFERROR(XLOOKUP(E59, '04_Products'!$A:$A, '04_Products'!$G:$G), 13.71) | H59: =IFERROR(XLOOKUP(E59, '04_Products'!$A:$A, '04_Products'!$F:$F), 0) | I59: =F59*G59 | J59: 0.05 | K59: =I59*J59 | L59: =I59-K59 | M59: =F59*H59 | N59: =L59-M59 | O59: =IFERROR(N59/L59, 0) | P59: =YEAR(C59) | Q59: =TEXT(C59, "yyyy-mm") | R59: Mobile App | S59: REG-NA
A60: DTL-0000057 | B60: ORD-000030 | C60: 2023-05-09 | D60: CUST-00164 | E60: PRD-0407 | F60: 1 | G60: =IFERROR(XLOOKUP(E60, '04_Products'!$A:$A, '04_Products'!$G:$G), 515.93) | H60: =IFERROR(XLOOKUP(E60, '04_Products'!$A:$A, '04_Products'!$F:$F), 0) | I60: =F60*G60 | J60: 0.1 | K60: =I60*J60 | L60: =I60-K60 | M60: =F60*H60 | N60: =L60-M60 | O60: =IFERROR(N60/L60, 0) | P60: =YEAR(C60) | Q60: =TEXT(C60, "yyyy-mm") | R60: Mobile App | S60: REG-NA
A61: DTL-0000058 | B61: ORD-000030 | C61: 2023-05-09 | D61: CUST-00164 | E61: PRD-0395 | F61: 1 | G61: =IFERROR(XLOOKUP(E61, '04_Products'!$A:$A, '04_Products'!$G:$G), 875.57) | H61: =IFERROR(XLOOKUP(E61, '04_Products'!$A:$A, '04_Products'!$F:$F), 0) | I61: =F61*G61 | J61: 0 | K61: =I61*J61 | L61: =I61-K61 | M61: =F61*H61 | N61: =L61-M61 | O61: =IFERROR(N61/L61, 0) | P61: =YEAR(C61) | Q61: =TEXT(C61, "yyyy-mm") | R61: Mobile App | S61: REG-NA
A62: DTL-0000059 | B62: ORD-000030 | C62: 2023-05-09 | D62: CUST-00164 | E62: PRD-0432 | F62: 3 | G62: =IFERROR(XLOOKUP(E62, '04_Products'!$A:$A, '04_Products'!$G:$G), 25.28) | H62: =IFERROR(XLOOKUP(E62, '04_Products'!$A:$A, '04_Products'!$F:$F), 0) | I62: =F62*G62 | J62: 0.05 | K62: =I62*J62 | L62: =I62-K62 | M62: =F62*H62 | N62: =L62-M62 | O62: =IFERROR(N62/L62, 0) | P62: =YEAR(C62) | Q62: =TEXT(C62, "yyyy-mm") | R62: Mobile App | S62: REG-NA
A63: DTL-0000060 | B63: ORD-000031 | C63: 2024-02-15 | D63: CUST-04504 | E63: PRD-0194 | F63: 1 | G63: =IFERROR(XLOOKUP(E63, '04_Products'!$A:$A, '04_Products'!$G:$G), 603.69) | H63: =IFERROR(XLOOKUP(E63, '04_Products'!$A:$A, '04_Products'!$F:$F), 0) | I63: =F63*G63 | J63: 0 | K63: =I63*J63 | L63: =I63-K63 | M63: =F63*H63 | N63: =L63-M63 | O63: =IFERROR(N63/L63, 0) | P63: =YEAR(C63) | Q63: =TEXT(C63, "yyyy-mm") | R63: B2B Portal | S63: REG-LATAM
A64: DTL-0000061 | B64: ORD-000032 | C64: 2025-09-03 | D64: CUST-01521 | E64: PRD-0023 | F64: 1 | G64: =IFERROR(XLOOKUP(E64, '04_Products'!$A:$A, '04_Products'!$G:$G), 276.60) | H64: =IFERROR(XLOOKUP(E64, '04_Products'!$A:$A, '04_Products'!$F:$F), 0) | I64: =F64*G64 | J64: 0 | K64: =I64*J64 | L64: =I64-K64 | M64: =F64*H64 | N64: =L64-M64 | O64: =IFERROR(N64/L64, 0) | P64: =YEAR(C64) | Q64: =TEXT(C64, "yyyy-mm") | R64: Direct Web | S64: REG-NA
A65: DTL-0000062 | B65: ORD-000032 | C65: 2025-09-03 | D65: CUST-01521 | E65: PRD-0021 | F65: 2 | G65: =IFERROR(XLOOKUP(E65, '04_Products'!$A:$A, '04_Products'!$G:$G), 41.09) | H65: =IFERROR(XLOOKUP(E65, '04_Products'!$A:$A, '04_Products'!$F:$F), 0) | I65: =F65*G65 | J65: 0.1 | K65: =I65*J65 | L65: =I65-K65 | M65: =F65*H65 | N65: =L65-M65 | O65: =IFERROR(N65/L65, 0) | P65: =YEAR(C65) | Q65: =TEXT(C65, "yyyy-mm") | R65: Direct Web | S65: REG-NA
A66: DTL-0000063 | B66: ORD-000033 | C66: 2025-03-19 | D66: CUST-04177 | E66: PRD-0421 | F66: 1 | G66: =IFERROR(XLOOKUP(E66, '04_Products'!$A:$A, '04_Products'!$G:$G), 50.08) | H66: =IFERROR(XLOOKUP(E66, '04_Products'!$A:$A, '04_Products'!$F:$F), 0) | I66: =F66*G66 | J66: 0.05 | K66: =I66*J66 | L66: =I66-K66 | M66: =F66*H66 | N66: =L66-M66 | O66: =IFERROR(N66/L66, 0) | P66: =YEAR(C66) | Q66: =TEXT(C66, "yyyy-mm") | R66: Mobile App | S66: REG-NA
A67: DTL-0000064 | B67: ORD-000033 | C67: 2025-03-19 | D67: CUST-04177 | E67: PRD-0311 | F67: 1 | G67: =IFERROR(XLOOKUP(E67, '04_Products'!$A:$A, '04_Products'!$G:$G), 7.85) | H67: =IFERROR(XLOOKUP(E67, '04_Products'!$A:$A, '04_Products'!$F:$F), 0) | I67: =F67*G67 | J67: 0 | K67: =I67*J67 | L67: =I67-K67 | M67: =F67*H67 | N67: =L67-M67 | O67: =IFERROR(N67/L67, 0) | P67: =YEAR(C67) | Q67: =TEXT(C67, "yyyy-mm") | R67: Mobile App | S67: REG-NA
A68: DTL-0000065 | B68: ORD-000033 | C68: 2025-03-19 | D68: CUST-04177 | E68: PRD-0402 | F68: 1 | G68: =IFERROR(XLOOKUP(E68, '04_Products'!$A:$A, '04_Products'!$G:$G), 1065.19) | H68: =IFERROR(XLOOKUP(E68, '04_Products'!$A:$A, '04_Products'!$F:$F), 0) | I68: =F68*G68 | J68: 0.05 | K68: =I68*J68 | L68: =I68-K68 | M68: =F68*H68 | N68: =L68-M68 | O68: =IFERROR(N68/L68, 0) | P68: =YEAR(C68) | Q68: =TEXT(C68, "yyyy-mm") | R68: Mobile App | S68: REG-NA
A69: DTL-0000066 | B69: ORD-000034 | C69: 2023-06-23 | D69: CUST-01453 | E69: PRD-0190 | F69: 1 | G69: =IFERROR(XLOOKUP(E69, '04_Products'!$A:$A, '04_Products'!$G:$G), 33.02) | H69: =IFERROR(XLOOKUP(E69, '04_Products'!$A:$A, '04_Products'!$F:$F), 0) | I69: =F69*G69 | J69: 0.2 | K69: =I69*J69 | L69: =I69-K69 | M69: =F69*H69 | N69: =L69-M69 | O69: =IFERROR(N69/L69, 0) | P69: =YEAR(C69) | Q69: =TEXT(C69, "yyyy-mm") | R69: Direct Web | S69: REG-NA
A70: DTL-0000067 | B70: ORD-000035 | C70: 2025-12-08 | D70: CUST-00357 | E70: PRD-0141 | F70: 1 | G70: =IFERROR(XLOOKUP(E70, '04_Products'!$A:$A, '04_Products'!$G:$G), 53.70) | H70: =IFERROR(XLOOKUP(E70, '04_Products'!$A:$A, '04_Products'!$F:$F), 0) | I70: =F70*G70 | J70: 0 | K70: =I70*J70 | L70: =I70-K70 | M70: =F70*H70 | N70: =L70-M70 | O70: =IFERROR(N70/L70, 0) | P70: =YEAR(C70) | Q70: =TEXT(C70, "yyyy-mm") | R70: Direct Web | S70: REG-NA
A71: DTL-0000068 | B71: ORD-000035 | C71: 2025-12-08 | D71: CUST-00357 | E71: PRD-0454 | F71: 1 | G71: =IFERROR(XLOOKUP(E71, '04_Products'!$A:$A, '04_Products'!$G:$G), 745.94) | H71: =IFERROR(XLOOKUP(E71, '04_Products'!$A:$A, '04_Products'!$F:$F), 0) | I71: =F71*G71 | J71: 0.2 | K71: =I71*J71 | L71: =I71-K71 | M71: =F71*H71 | N71: =L71-M71 | O71: =IFERROR(N71/L71, 0) | P71: =YEAR(C71) | Q71: =TEXT(C71, "yyyy-mm") | R71: Direct Web | S71: REG-NA
A72: DTL-0000069 | B72: ORD-000036 | C72: 2025-06-21 | D72: CUST-06211 | E72: PRD-0106 | F72: 1 | G72: =IFERROR(XLOOKUP(E72, '04_Products'!$A:$A, '04_Products'!$G:$G), 49.14) | H72: =IFERROR(XLOOKUP(E72, '04_Products'!$A:$A, '04_Products'!$F:$F), 0) | I72: =F72*G72 | J72: 0.1 | K72: =I72*J72 | L72: =I72-K72 | M72: =F72*H72 | N72: =L72-M72 | O72: =IFERROR(N72/L72, 0) | P72: =YEAR(C72) | Q72: =TEXT(C72, "yyyy-mm") | R72: Direct Web | S72: REG-NA
A73: DTL-0000070 | B73: ORD-000036 | C73: 2025-06-21 | D73: CUST-06211 | E73: PRD-0288 | F73: 1 | G73: =IFERROR(XLOOKUP(E73, '04_Products'!$A:$A, '04_Products'!$G:$G), 41.37) | H73: =IFERROR(XLOOKUP(E73, '04_Products'!$A:$A, '04_Products'!$F:$F), 0) | I73: =F73*G73 | J73: 0 | K73: =I73*J73 | L73: =I73-K73 | M73: =F73*H73 | N73: =L73-M73 | O73: =IFERROR(N73/L73, 0) | P73: =YEAR(C73) | Q73: =TEXT(C73, "yyyy-mm") | R73: Direct Web | S73: REG-NA
A74: DTL-0000071 | B74: ORD-000036 | C74: 2025-06-21 | D74: CUST-06211 | E74: PRD-0357 | F74: 1 | G74: =IFERROR(XLOOKUP(E74, '04_Products'!$A:$A, '04_Products'!$G:$G), 305.71) | H74: =IFERROR(XLOOKUP(E74, '04_Products'!$A:$A, '04_Products'!$F:$F), 0) | I74: =F74*G74 | J74: 0 | K74: =I74*J74 | L74: =I74-K74 | M74: =F74*H74 | N74: =L74-M74 | O74: =IFERROR(N74/L74, 0) | P74: =YEAR(C74) | Q74: =TEXT(C74, "yyyy-mm") | R74: Direct Web | S74: REG-NA
A75: DTL-0000072 | B75: ORD-000037 | C75: 2023-06-08 | D75: CUST-07906 | E75: PRD-0229 | F75: 2 | G75: =IFERROR(XLOOKUP(E75, '04_Products'!$A:$A, '04_Products'!$G:$G), 31.96) | H75: =IFERROR(XLOOKUP(E75, '04_Products'!$A:$A, '04_Products'!$F:$F), 0) | I75: =F75*G75 | J75: 0.05 | K75: =I75*J75 | L75: =I75-K75 | M75: =F75*H75 | N75: =L75-M75 | O75: =IFERROR(N75/L75, 0) | P75: =YEAR(C75) | Q75: =TEXT(C75, "yyyy-mm") | R75: Affiliate Partner | S75: REG-APAC
A76: DTL-0000073 | B76: ORD-000038 | C76: 2023-11-24 | D76: CUST-04333 | E76: PRD-0369 | F76: 1 | G76: =IFERROR(XLOOKUP(E76, '04_Products'!$A:$A, '04_Products'!$G:$G), 653.11) | H76: =IFERROR(XLOOKUP(E76, '04_Products'!$A:$A, '04_Products'!$F:$F), 0) | I76: =F76*G76 | J76: 0 | K76: =I76*J76 | L76: =I76-K76 | M76: =F76*H76 | N76: =L76-M76 | O76: =IFERROR(N76/L76, 0) | P76: =YEAR(C76) | Q76: =TEXT(C76, "yyyy-mm") | R76: B2B Portal | S76: REG-NA
A77: DTL-0000074 | B77: ORD-000038 | C77: 2023-11-24 | D77: CUST-04333 | E77: PRD-0207 | F77: 1 | G77: =IFERROR(XLOOKUP(E77, '04_Products'!$A:$A, '04_Products'!$G:$G), 1025.22) | H77: =IFERROR(XLOOKUP(E77, '04_Products'!$A:$A, '04_Products'!$F:$F), 0) | I77: =F77*G77 | J77: 0 | K77: =I77*J77 | L77: =I77-K77 | M77: =F77*H77 | N77: =L77-M77 | O77: =IFERROR(N77/L77, 0) | P77: =YEAR(C77) | Q77: =TEXT(C77, "yyyy-mm") | R77: B2B Portal | S77: REG-NA
A78: DTL-0000075 | B78: ORD-000039 | C78: 2024-09-09 | D78: CUST-01549 | E78: PRD-0111 | F78: 1 | G78: =IFERROR(XLOOKUP(E78, '04_Products'!$A:$A, '04_Products'!$G:$G), 63.37) | H78: =IFERROR(XLOOKUP(E78, '04_Products'!$A:$A, '04_Products'!$F:$F), 0) | I78: =F78*G78 | J78: 0.1 | K78: =I78*J78 | L78: =I78-K78 | M78: =F78*H78 | N78: =L78-M78 | O78: =IFERROR(N78/L78, 0) | P78: =YEAR(C78) | Q78: =TEXT(C78, "yyyy-mm") | R78: Direct Web | S78: REG-APAC
A79: DTL-0000076 | B79: ORD-000040 | C79: 2025-08-26 | D79: CUST-04796 | E79: PRD-0182 | F79: 1 | G79: =IFERROR(XLOOKUP(E79, '04_Products'!$A:$A, '04_Products'!$G:$G), 1423.65) | H79: =IFERROR(XLOOKUP(E79, '04_Products'!$A:$A, '04_Products'!$F:$F), 0) | I79: =F79*G79 | J79: 0 | K79: =I79*J79 | L79: =I79-K79 | M79: =F79*H79 | N79: =L79-M79 | O79: =IFERROR(N79/L79, 0) | P79: =YEAR(C79) | Q79: =TEXT(C79, "yyyy-mm") | R79: B2B Portal | S79: REG-APAC
A80: DTL-0000077 | B80: ORD-000041 | C80: 2025-09-13 | D80: CUST-06011 | E80: PRD-0318 | F80: 2 | G80: =IFERROR(XLOOKUP(E80, '04_Products'!$A:$A, '04_Products'!$G:$G), 130.98) | H80: =IFERROR(XLOOKUP(E80, '04_Products'!$A:$A, '04_Products'!$F:$F), 0) | I80: =F80*G80 | J80: 0.05 | K80: =I80*J80 | L80: =I80-K80 | M80: =F80*H80 | N80: =L80-M80 | O80: =IFERROR(N80/L80, 0) | P80: =YEAR(C80) | Q80: =TEXT(C80, "yyyy-mm") | R80: Mobile App | S80: REG-EU
A81: DTL-0000078 | B81: ORD-000042 | C81: 2023-03-01 | D81: CUST-07356 | E81: PRD-0434 | F81: 1 | G81: =IFERROR(XLOOKUP(E81, '04_Products'!$A:$A, '04_Products'!$G:$G), 899.59) | H81: =IFERROR(XLOOKUP(E81, '04_Products'!$A:$A, '04_Products'!$F:$F), 0) | I81: =F81*G81 | J81: 0.15 | K81: =I81*J81 | L81: =I81-K81 | M81: =F81*H81 | N81: =L81-M81 | O81: =IFERROR(N81/L81, 0) | P81: =YEAR(C81) | Q81: =TEXT(C81, "yyyy-mm") | R81: Mobile App | S81: REG-EU
A82: DTL-0000079 | B82: ORD-000042 | C82: 2023-03-01 | D82: CUST-07356 | E82: PRD-0264 | F82: 1 | G82: =IFERROR(XLOOKUP(E82, '04_Products'!$A:$A, '04_Products'!$G:$G), 705.08) | H82: =IFERROR(XLOOKUP(E82, '04_Products'!$A:$A, '04_Products'!$F:$F), 0) | I82: =F82*G82 | J82: 0.1 | K82: =I82*J82 | L82: =I82-K82 | M82: =F82*H82 | N82: =L82-M82 | O82: =IFERROR(N82/L82, 0) | P82: =YEAR(C82) | Q82: =TEXT(C82, "yyyy-mm") | R82: Mobile App | S82: REG-EU
A83: DTL-0000080 | B83: ORD-000042 | C83: 2023-03-01 | D83: CUST-07356 | E83: PRD-0243 | F83: 2 | G83: =IFERROR(XLOOKUP(E83, '04_Products'!$A:$A, '04_Products'!$G:$G), 510.81) | H83: =IFERROR(XLOOKUP(E83, '04_Products'!$A:$A, '04_Products'!$F:$F), 0) | I83: =F83*G83 | J83: 0.1 | K83: =I83*J83 | L83: =I83-K83 | M83: =F83*H83 | N83: =L83-M83 | O83: =IFERROR(N83/L83, 0) | P83: =YEAR(C83) | Q83: =TEXT(C83, "yyyy-mm") | R83: Mobile App | S83: REG-EU
A84: DTL-0000081 | B84: ORD-000042 | C84: 2023-03-01 | D84: CUST-07356 | E84: PRD-0329 | F84: 1 | G84: =IFERROR(XLOOKUP(E84, '04_Products'!$A:$A, '04_Products'!$G:$G), 1014.02) | H84: =IFERROR(XLOOKUP(E84, '04_Products'!$A:$A, '04_Products'!$F:$F), 0) | I84: =F84*G84 | J84: 0 | K84: =I84*J84 | L84: =I84-K84 | M84: =F84*H84 | N84: =L84-M84 | O84: =IFERROR(N84/L84, 0) | P84: =YEAR(C84) | Q84: =TEXT(C84, "yyyy-mm") | R84: Mobile App | S84: REG-EU
A85: DTL-0000082 | B85: ORD-000043 | C85: 2024-01-11 | D85: CUST-04116 | E85: PRD-0256 | F85: 2 | G85: =IFERROR(XLOOKUP(E85, '04_Products'!$A:$A, '04_Products'!$G:$G), 235.18) | H85: =IFERROR(XLOOKUP(E85, '04_Products'!$A:$A, '04_Products'!$F:$F), 0) | I85: =F85*G85 | J85: 0 | K85: =I85*J85 | L85: =I85-K85 | M85: =F85*H85 | N85: =L85-M85 | O85: =IFERROR(N85/L85, 0) | P85: =YEAR(C85) | Q85: =TEXT(C85, "yyyy-mm") | R85: Direct Web | S85: REG-APAC
A86: DTL-0000083 | B86: ORD-000043 | C86: 2024-01-11 | D86: CUST-04116 | E86: PRD-0332 | F86: 1 | G86: =IFERROR(XLOOKUP(E86, '04_Products'!$A:$A, '04_Products'!$G:$G), 82.03) | H86: =IFERROR(XLOOKUP(E86, '04_Products'!$A:$A, '04_Products'!$F:$F), 0) | I86: =F86*G86 | J86: 0 | K86: =I86*J86 | L86: =I86-K86 | M86: =F86*H86 | N86: =L86-M86 | O86: =IFERROR(N86/L86, 0) | P86: =YEAR(C86) | Q86: =TEXT(C86, "yyyy-mm") | R86: Direct Web | S86: REG-APAC
A87: DTL-0000084 | B87: ORD-000044 | C87: 2024-04-29 | D87: CUST-01005 | E87: PRD-0273 | F87: 1 | G87: =IFERROR(XLOOKUP(E87, '04_Products'!$A:$A, '04_Products'!$G:$G), 19.23) | H87: =IFERROR(XLOOKUP(E87, '04_Products'!$A:$A, '04_Products'!$F:$F), 0) | I87: =F87*G87 | J87: 0.2 | K87: =I87*J87 | L87: =I87-K87 | M87: =F87*H87 | N87: =L87-M87 | O87: =IFERROR(N87/L87, 0) | P87: =YEAR(C87) | Q87: =TEXT(C87, "yyyy-mm") | R87: Direct Web | S87: REG-NA
A88: DTL-0000085 | B88: ORD-000045 | C88: 2024-04-28 | D88: CUST-02201 | E88: PRD-0464 | F88: 2 | G88: =IFERROR(XLOOKUP(E88, '04_Products'!$A:$A, '04_Products'!$G:$G), 21.08) | H88: =IFERROR(XLOOKUP(E88, '04_Products'!$A:$A, '04_Products'!$F:$F), 0) | I88: =F88*G88 | J88: 0.15 | K88: =I88*J88 | L88: =I88-K88 | M88: =F88*H88 | N88: =L88-M88 | O88: =IFERROR(N88/L88, 0) | P88: =YEAR(C88) | Q88: =TEXT(C88, "yyyy-mm") | R88: Direct Web | S88: REG-NA
A89: DTL-0000086 | B89: ORD-000046 | C89: 2025-09-10 | D89: CUST-07566 | E89: PRD-0250 | F89: 1 | G89: =IFERROR(XLOOKUP(E89, '04_Products'!$A:$A, '04_Products'!$G:$G), 91.75) | H89: =IFERROR(XLOOKUP(E89, '04_Products'!$A:$A, '04_Products'!$F:$F), 0) | I89: =F89*G89 | J89: 0.1 | K89: =I89*J89 | L89: =I89-K89 | M89: =F89*H89 | N89: =L89-M89 | O89: =IFERROR(N89/L89, 0) | P89: =YEAR(C89) | Q89: =TEXT(C89, "yyyy-mm") | R89: Direct Web | S89: REG-NA
A90: DTL-0000087 | B90: ORD-000047 | C90: 2025-11-03 | D90: CUST-00902 | E90: PRD-0496 | F90: 1 | G90: =IFERROR(XLOOKUP(E90, '04_Products'!$A:$A, '04_Products'!$G:$G), 555.47) | H90: =IFERROR(XLOOKUP(E90, '04_Products'!$A:$A, '04_Products'!$F:$F), 0) | I90: =F90*G90 | J90: 0 | K90: =I90*J90 | L90: =I90-K90 | M90: =F90*H90 | N90: =L90-M90 | O90: =IFERROR(N90/L90, 0) | P90: =YEAR(C90) | Q90: =TEXT(C90, "yyyy-mm") | R90: Direct Web | S90: REG-EU
A91: DTL-0000088 | B91: ORD-000047 | C91: 2025-11-03 | D91: CUST-00902 | E91: PRD-0197 | F91: 2 | G91: =IFERROR(XLOOKUP(E91, '04_Products'!$A:$A, '04_Products'!$G:$G), 810.85) | H91: =IFERROR(XLOOKUP(E91, '04_Products'!$A:$A, '04_Products'!$F:$F), 0) | I91: =F91*G91 | J91: 0.1 | K91: =I91*J91 | L91: =I91-K91 | M91: =F91*H91 | N91: =L91-M91 | O91: =IFERROR(N91/L91, 0) | P91: =YEAR(C91) | Q91: =TEXT(C91, "yyyy-mm") | R91: Direct Web | S91: REG-EU
A92: DTL-0000089 | B92: ORD-000048 | C92: 2024-03-21 | D92: CUST-03522 | E92: PRD-0451 | F92: 1 | G92: =IFERROR(XLOOKUP(E92, '04_Products'!$A:$A, '04_Products'!$G:$G), 664.94) | H92: =IFERROR(XLOOKUP(E92, '04_Products'!$A:$A, '04_Products'!$F:$F), 0) | I92: =F92*G92 | J92: 0 | K92: =I92*J92 | L92: =I92-K92 | M92: =F92*H92 | N92: =L92-M92 | O92: =IFERROR(N92/L92, 0) | P92: =YEAR(C92) | Q92: =TEXT(C92, "yyyy-mm") | R92: Direct Web | S92: REG-EU
A93: DTL-0000090 | B93: ORD-000049 | C93: 2024-11-13 | D93: CUST-01209 | E93: PRD-0482 | F93: 1 | G93: =IFERROR(XLOOKUP(E93, '04_Products'!$A:$A, '04_Products'!$G:$G), 1206.95) | H93: =IFERROR(XLOOKUP(E93, '04_Products'!$A:$A, '04_Products'!$F:$F), 0) | I93: =F93*G93 | J93: 0.15 | K93: =I93*J93 | L93: =I93-K93 | M93: =F93*H93 | N93: =L93-M93 | O93: =IFERROR(N93/L93, 0) | P93: =YEAR(C93) | Q93: =TEXT(C93, "yyyy-mm") | R93: Direct Web | S93: REG-EU
A94: DTL-0000091 | B94: ORD-000049 | C94: 2024-11-13 | D94: CUST-01209 | E94: PRD-0331 | F94: 2 | G94: =IFERROR(XLOOKUP(E94, '04_Products'!$A:$A, '04_Products'!$G:$G), 1076.14) | H94: =IFERROR(XLOOKUP(E94, '04_Products'!$A:$A, '04_Products'!$F:$F), 0) | I94: =F94*G94 | J94: 0 | K94: =I94*J94 | L94: =I94-K94 | M94: =F94*H94 | N94: =L94-M94 | O94: =IFERROR(N94/L94, 0) | P94: =YEAR(C94) | Q94: =TEXT(C94, "yyyy-mm") | R94: Direct Web | S94: REG-EU
A95: DTL-0000092 | B95: ORD-000049 | C95: 2024-11-13 | D95: CUST-01209 | E95: PRD-0338 | F95: 1 | G95: =IFERROR(XLOOKUP(E95, '04_Products'!$A:$A, '04_Products'!$G:$G), 76.99) | H95: =IFERROR(XLOOKUP(E95, '04_Products'!$A:$A, '04_Products'!$F:$F), 0) | I95: =F95*G95 | J95: 0.1 | K95: =I95*J95 | L95: =I95-K95 | M95: =F95*H95 | N95: =L95-M95 | O95: =IFERROR(N95/L95, 0) | P95: =YEAR(C95) | Q95: =TEXT(C95, "yyyy-mm") | R95: Direct Web | S95: REG-EU
A96: DTL-0000093 | B96: ORD-000050 | C96: 2025-08-03 | D96: CUST-00567 | E96: PRD-0205 | F96: 1 | G96: =IFERROR(XLOOKUP(E96, '04_Products'!$A:$A, '04_Products'!$G:$G), 385.35) | H96: =IFERROR(XLOOKUP(E96, '04_Products'!$A:$A, '04_Products'!$F:$F), 0) | I96: =F96*G96 | J96: 0.15 | K96: =I96*J96 | L96: =I96-K96 | M96: =F96*H96 | N96: =L96-M96 | O96: =IFERROR(N96/L96, 0) | P96: =YEAR(C96) | Q96: =TEXT(C96, "yyyy-mm") | R96: Affiliate Partner | S96: REG-EU
A97: DTL-0000094 | B97: ORD-000051 | C97: 2024-10-13 | D97: CUST-05267 | E97: PRD-0401 | F97: 2 | G97: =IFERROR(XLOOKUP(E97, '04_Products'!$A:$A, '04_Products'!$G:$G), 57.89) | H97: =IFERROR(XLOOKUP(E97, '04_Products'!$A:$A, '04_Products'!$F:$F), 0) | I97: =F97*G97 | J97: 0.05 | K97: =I97*J97 | L97: =I97-K97 | M97: =F97*H97 | N97: =L97-M97 | O97: =IFERROR(N97/L97, 0) | P97: =YEAR(C97) | Q97: =TEXT(C97, "yyyy-mm") | R97: Direct Web | S97: REG-EU
A98: DTL-0000095 | B98: ORD-000051 | C98: 2024-10-13 | D98: CUST-05267 | E98: PRD-0498 | F98: 1 | G98: =IFERROR(XLOOKUP(E98, '04_Products'!$A:$A, '04_Products'!$G:$G), 63.17) | H98: =IFERROR(XLOOKUP(E98, '04_Products'!$A:$A, '04_Products'!$F:$F), 0) | I98: =F98*G98 | J98: 0 | K98: =I98*J98 | L98: =I98-K98 | M98: =F98*H98 | N98: =L98-M98 | O98: =IFERROR(N98/L98, 0) | P98: =YEAR(C98) | Q98: =TEXT(C98, "yyyy-mm") | R98: Direct Web | S98: REG-EU
A99: DTL-0000096 | B99: ORD-000052 | C99: 2025-11-30 | D99: CUST-00389 | E99: PRD-0239 | F99: 3 | G99: =IFERROR(XLOOKUP(E99, '04_Products'!$A:$A, '04_Products'!$G:$G), 302.56) | H99: =IFERROR(XLOOKUP(E99, '04_Products'!$A:$A, '04_Products'!$F:$F), 0) | I99: =F99*G99 | J99: 0 | K99: =I99*J99 | L99: =I99-K99 | M99: =F99*H99 | N99: =L99-M99 | O99: =IFERROR(N99/L99, 0) | P99: =YEAR(C99) | Q99: =TEXT(C99, "yyyy-mm") | R99: Direct Web | S99: REG-NA
A100: DTL-0000097 | B100: ORD-000053 | C100: 2024-11-17 | D100: CUST-07677 | E100: PRD-0297 | F100: 3 | G100: =IFERROR(XLOOKUP(E100, '04_Products'!$A:$A, '04_Products'!$G:$G), 47.74) | H100: =IFERROR(XLOOKUP(E100, '04_Products'!$A:$A, '04_Products'!$F:$F), 0) | I100: =F100*G100 | J100: 0.1 | K100: =I100*J100 | L100: =I100-K100 | M100: =F100*H100 | N100: =L100-M100 | O100: =IFERROR(N100/L100, 0) | P100: =YEAR(C100) | Q100: =TEXT(C100, "yyyy-mm") | R100: Direct Web | S100: REG-NA
A101: DTL-0000098 | B101: ORD-000054 | C101: 2024-04-08 | D101: CUST-04127 | E101: PRD-0250 | F101: 1 | G101: =IFERROR(XLOOKUP(E101, '04_Products'!$A:$A, '04_Products'!$G:$G), 91.75) | H101: =IFERROR(XLOOKUP(E101, '04_Products'!$A:$A, '04_Products'!$F:$F), 0) | I101: =F101*G101 | J101: 0 | K101: =I101*J101 | L101: =I101-K101 | M101: =F101*H101 | N101: =L101-M101 | O101: =IFERROR(N101/L101, 0) | P101: =YEAR(C101) | Q101: =TEXT(C101, "yyyy-mm") | R101: Mobile App | S101: REG-NA
...

Sheet 06_Pivot_Analysis
A1: SAMPLE PIVOT & MULTI-DIMENSIONAL ANALYSIS
A2: Formula-based sample analysis of the 2,000 order lines in 05_Orders; see 09_Warehouse_KPIs for full-warehouse totals.
A4: 1. ANNUAL REVENUE & PROFIT SUMMARY
A5: Fiscal Year | B5: Total Orders | C5: Units Sold | D5: Gross Sales | E5: Discount Given | F5: Net Revenue | G5: Total COGS | H5: Net Profit | I5: Profit Margin %
A6: 2023 | B6: =COUNTIFS('05_Orders'!$P:$P, A6) | C6: =SUMIFS('05_Orders'!$F:$F, '05_Orders'!$P:$P, A6) | D6: =SUMIFS('05_Orders'!$I:$I, '05_Orders'!$P:$P, A6) | E6: =SUMIFS('05_Orders'!$K:$K, '05_Orders'!$P:$P, A6) | F6: =SUMIFS('05_Orders'!$L:$L, '05_Orders'!$P:$P, A6) | G6: =SUMIFS('05_Orders'!$M:$M, '05_Orders'!$P:$P, A6) | H6: =SUMIFS('05_Orders'!$N:$N, '05_Orders'!$P:$P, A6) | I6: =IFERROR(H6/F6, 0)
A7: 2024 | B7: =COUNTIFS('05_Orders'!$P:$P, A7) | C7: =SUMIFS('05_Orders'!$F:$F, '05_Orders'!$P:$P, A7) | D7: =SUMIFS('05_Orders'!$I:$I, '05_Orders'!$P:$P, A7) | E7: =SUMIFS('05_Orders'!$K:$K, '05_Orders'!$P:$P, A7) | F7: =SUMIFS('05_Orders'!$L:$L, '05_Orders'!$P:$P, A7) | G7: =SUMIFS('05_Orders'!$M:$M, '05_Orders'!$P:$P, A7) | H7: =SUMIFS('05_Orders'!$N:$N, '05_Orders'!$P:$P, A7) | I7: =IFERROR(H7/F7, 0)
A8: 2025 | B8: =COUNTIFS('05_Orders'!$P:$P, A8) | C8: =SUMIFS('05_Orders'!$F:$F, '05_Orders'!$P:$P, A8) | D8: =SUMIFS('05_Orders'!$I:$I, '05_Orders'!$P:$P, A8) | E8: =SUMIFS('05_Orders'!$K:$K, '05_Orders'!$P:$P, A8) | F8: =SUMIFS('05_Orders'!$L:$L, '05_Orders'!$P:$P, A8) | G8: =SUMIFS('05_Orders'!$M:$M, '05_Orders'!$P:$P, A8) | H8: =SUMIFS('05_Orders'!$N:$N, '05_Orders'!$P:$P, A8) | I8: =IFERROR(H8/F8, 0)
A9: Total Enterprise | B9: =SUM(B6:B8) | C9: =SUM(C6:C8) | D9: =SUM(D6:D8) | E9: =SUM(E6:E8) | F9: =SUM(F6:F8) | G9: =SUM(G6:G8) | H9: =SUM(H6:H8) | I9: =IFERROR(H9/F9, 0)
A11: 2. REGIONAL PERFORMANCE & MARGIN CONTRIBUTION
A12: Region Code | B12: Region Name | C12: Net Revenue | D12: Net Profit | E12: Profit Margin % | F12: Revenue Share %
A13: REG-NA | B13: North America | C13: =SUMIFS('05_Orders'!$L:$L, '05_Orders'!$S:$S, A13) | D13: =SUMIFS('05_Orders'!$N:$N, '05_Orders'!$S:$S, A13) | E13: =IFERROR(D13/C13, 0) | F13: =IFERROR(C13/$F$9, 0)
A14: REG-EU | B14: Europe | C14: =SUMIFS('05_Orders'!$L:$L, '05_Orders'!$S:$S, A14) | D14: =SUMIFS('05_Orders'!$N:$N, '05_Orders'!$S:$S, A14) | E14: =IFERROR(D14/C14, 0) | F14: =IFERROR(C14/$F$9, 0)
A15: REG-APAC | B15: Asia-Pacific | C15: =SUMIFS('05_Orders'!$L:$L, '05_Orders'!$S:$S, A15) | D15: =SUMIFS('05_Orders'!$N:$N, '05_Orders'!$S:$S, A15) | E15: =IFERROR(D15/C15, 0) | F15: =IFERROR(C15/$F$9, 0)
A16: REG-LATAM | B16: Latin America | C16: =SUMIFS('05_Orders'!$L:$L, '05_Orders'!$S:$S, A16) | D16: =SUMIFS('05_Orders'!$N:$N, '05_Orders'!$S:$S, A16) | E16: =IFERROR(D16/C16, 0) | F16: =IFERROR(C16/$F$9, 0)
A19: 3. DISCOUNT ELASTICITY & MARGIN EROSION ANALYSIS
A20: Discount Tier | B20: Transaction Count | C20: Net Revenue | D20: Total Profit | E20: Realized Margin % | F20: Pricing Health
A21: 0% Full Price | B21: =COUNTIFS('05_Orders'!$J:$J, 0) | C21: =SUMIFS('05_Orders'!$L:$L, '05_Orders'!$J:$J, 0) | D21: =SUMIFS('05_Orders'!$N:$N, '05_Orders'!$J:$J, 0) | E21: =IFERROR(D21/C21, 0) | F21: =IF(E21>=0.25, "Highly Profitable", IF(E21>=0.15, "Acceptable", "Margin Drag Alert"))
A22: 1% - 10% Low Discount | B22: =COUNTIFS('05_Orders'!$J:$J, ">=0.01", '05_Orders'!$J:$J, "<=0.1") | C22: =SUMIFS('05_Orders'!$L:$L, '05_Orders'!$J:$J, ">=0.01", '05_Orders'!$J:$J, "<=0.1") | D22: =SUMIFS('05_Orders'!$N:$N, '05_Orders'!$J:$J, ">=0.01", '05_Orders'!$J:$J, "<=0.1") | E22: =IFERROR(D22/C22, 0) | F22: =IF(E22>=0.25, "Highly Profitable", IF(E22>=0.15, "Acceptable", "Margin Drag Alert"))
A23: 11% - 20% Moderate Discount | B23: =COUNTIFS('05_Orders'!$J:$J, ">=0.11", '05_Orders'!$J:$J, "<=0.2") | C23: =SUMIFS('05_Orders'!$L:$L, '05_Orders'!$J:$J, ">=0.11", '05_Orders'!$J:$J, "<=0.2") | D23: =SUMIFS('05_Orders'!$N:$N, '05_Orders'!$J:$J, ">=0.11", '05_Orders'!$J:$J, "<=0.2") | E23: =IFERROR(D23/C23, 0) | F23: =IF(E23>=0.25, "Highly Profitable", IF(E23>=0.15, "Acceptable", "Margin Drag Alert"))
A24: > 20% High Discount | B24: =COUNTIFS('05_Orders'!$J:$J, ">=0.21", '05_Orders'!$J:$J, "<=1.0") | C24: =SUMIFS('05_Orders'!$L:$L, '05_Orders'!$J:$J, ">=0.21", '05_Orders'!$J:$J, "<=1.0") | D24: =SUMIFS('05_Orders'!$N:$N, '05_Orders'!$J:$J, ">=0.21", '05_Orders'!$J:$J, "<=1.0") | E24: =IFERROR(D24/C24, 0) | F24: =IF(E24>=0.25, "Highly Profitable", IF(E24>=0.15, "Acceptable", "Margin Drag Alert"))

Sheet 07_KPI_Summary
A1: SAMPLE KPI FORMULA EXAMPLES
A2: Formula examples based on the sample in 05_Orders; official full-warehouse metrics are in 09_Warehouse_KPIs.
A4: TOTAL NET REVENUE | C4: SAMPLE LINE-ITEM PROFIT | E4: PROFIT MARGIN % | G4: TOTAL ORDERS | I4: AVERAGE ORDER VALUE (AOV)
A5: ='06_Pivot_Analysis'!F9 | C5: ='06_Pivot_Analysis'!H9 | E5: ='06_Pivot_Analysis'!I9 | G5: ='06_Pivot_Analysis'!B9 | I5: =IFERROR('06_Pivot_Analysis'!F9/'06_Pivot_Analysis'!B9, 0)
A8: SAMPLE KPI FORMULAS (NO BUSINESS TARGETS SUPPLIED)
A9: Metric Name | B9: Sample Formula | C9: Target Supplied | D9: Variance | E9: Achievement | F9: Status
A10: Net Revenue | B10: ='06_Pivot_Analysis'!F9 | C10: No | F10: Not assessed
A11: Line-item profit | B11: ='06_Pivot_Analysis'!H9 | C11: No | F11: Not assessed
A12: Line-item margin % | B12: ='06_Pivot_Analysis'!I9 | C12: No | F12: Not assessed
A13: Average Order Value (AOV) | B13: =IFERROR('06_Pivot_Analysis'!F9/'06_Pivot_Analysis'!B9, 0) | C13: No | F13: Not assessed
A14: Discount Rate % | B14: =IFERROR('06_Pivot_Analysis'!E9/'06_Pivot_Analysis'!D9, 0) | C14: No | F14: Not assessed

Sheet 08_Business_Insights
A1: FULL-WAREHOUSE BUSINESS OBSERVATIONS
A2: Descriptive patterns from the current full warehouse; observations are not causal estimates, forecasts, or measured financial benefits.
A4: Observation # | B4: Domain | C4: Observed Pattern | D4: Quantitative Evidence | E4: Interpretation / Limitation | F4: Suggested Follow-up
A5: 1 | B5: Discount bands | C5: Higher discount bands have lower observed line-item margins. | D5: >20%: 6.5% across 6,288 lines; 0%: 31.3% across 39,702 lines. | E5: Association only; product and channel mix differ by discount tier. No incremental volume or causal elasticity was estimated. | F5: Review high-discount transactions and compare like-for-like products before changing discount policy.
A6: 2 | B6: Product mix | C6: Technology is the largest net-sales category. | D6: Technology: $41,025,397.18 (57.3% of net sales), 22.9% line margin; Office Supplies margin: 33.3%. | E6: Category margins describe stored line values before refunds; mix and cost differences are not controlled. | F6: Review category pricing, cost, and product mix together.
A7: 3 | B7: Regional mix | C7: North America has the highest net sales; regional margins are similar. | D7: North America: $29,702,500.47; regional line margins range 25.8%–26.1%. | E7: The current data shows a sales-scale difference, not a clear regional margin gap. | F7: Investigate market size, volume, and costs before reallocating spend.
A8: 4 | B8: Customer orders | C8: Most customers with order headers have two or more distinct orders. | D8: 7,891 of 7,986 customers (98.81%) have 2+ distinct order headers; 95 have one. | E8: Counts include every order status, including cancelled orders; this is not a completed-purchase retention rate. | F8: Recalculate retention using completed orders and a defined cohort window.
A9: 5 | B9: Returns | C9: Recorded returns total more than one and a half million dollars in refunds. | D9: 2,983 incidents, 4,172 units (2.21% of line units), $1,545,024.47 refunded. Most incidents: Damaged in Transit (521); largest refund reason: Size / Fit Mismatch ($286,499.46). | E9: Refunds are recorded amounts; reverse freight, restocking, and other return costs are not modeled. | F9: Validate leading return reasons against operational and supplier records.
A10: 6 | B10: Inventory | C10: 64 SKUs are at or below their reorder levels in the latest snapshot. | D10: 2025-12-01: 132,045 closing units valued at $37,282,641.98 using product cost. | E10: Inventory is a monthly snapshot; its values are not attributed to region, sales channel, or customer segment. | F10: Review the flagged SKUs against lead times and replenishment plans.
A11: 7 | B11: Sales targets | C11: Aggregate net sales exceed the stored aggregate sales target. | D11: $71,564,192.67 net sales against $34,910,032.51 targets (205.0%); actuals include all order statuses. | E11: Actuals and targets should be aligned by period, region, and category; the overall ratio is not a channel/segment comparison. | F11: Validate status and target-scope alignment before using attainment for performance decisions.

Sheet 09_Warehouse_KPIs
A1: FULL-WAREHOUSE SQL RESULTS
A2: Static values from data/ecommerce_analytics.db at build time. Sales and line-item profit include cancelled orders; refunds are separate.
A4: Metric | B4: Full-warehouse value | C4: Definition / scope | E4: Warehouse table | F4: Rows
A5: Gross sales | B5: 77161512 | C5: Order-line gross sales before discounts. | E5: dim_category | F5: 15
A6: Discounts | B6: 5597319 | C6: Stored order-line discount amounts. | E6: dim_customer | F6: 8000
A7: Net sales | B7: 71564193 | C7: Gross sales less line-item discounts. | E7: dim_date | F7: 1096
A8: COGS | B8: 53032486 | C8: Stored order-line total cost. | E8: dim_product | F8: 500
A9: Line-item profit | B9: 18531707 | C9: Net sales less stored COGS; before refunds and operating expenses. | E9: dim_region | F9: 4
A10: Line-item margin | B10: 0.25895223 | C10: Line-item profit / net sales. | E10: fact_inventory | F10: 18000
A11: Distinct orders | B11: 51180 | C11: Distinct order IDs represented by order lines; all statuses. | E11: fact_order_details | F11: 104673
A12: Order-detail rows | B12: 104673 | C12: Rows in fact_order_details. | E12: fact_orders | F12: 51180
A13: Units on order lines | B13: 188832 | C13: Sum of quantity in fact_order_details. | E13: fact_returns | F13: 2983
A14: Average order value | B14: 1398.2843 | C14: Net sales / distinct order IDs represented by order lines. | E14: fact_sales_targets | F14: 576
A15: Customers with order headers | B15: 7986 | C15: Distinct customers in fact_orders; all statuses.
A16: Repeat customers | B16: 7891 | C16: Customers with 2+ distinct order headers.
A17: Repeat-customer rate | B17: 0.98810418 | C17: Repeat customers / customers with at least one order header. | E17: Order date range | F17: 2023-01-01 to 2025-12-31
A18: One-time customers | B18: 95 | C18: Customers with exactly one distinct order header.
A19: Return incidents | B19: 2983 | C19: Distinct return IDs.
A20: Returned units | B20: 4172 | C20: Sum of fact_returns.return_quantity.
A21: Return-unit rate | B21: 0.022093713 | C21: Returned units / units on all order-detail lines.
A22: Refunds | B22: 1545024.5 | C22: Recorded refund amounts.
A23: Refund-adjusted profit | B23: 16986683 | C23: Line-item profit less recorded refunds; not operating profit or EBITDA.
A24: Sales targets | B24: 34910033 | C24: Sum of fact_sales_targets.sales_target.
A25: Target attainment | B25: 2.0499606 | C25: Aggregate net sales / aggregate sales target; all order statuses.
A26: Latest inventory snapshot | B26: 2025-12-01 | C26: Maximum snapshot_date in fact_inventory.
A27: Latest closing units | B27: 132045 | C27: Closing stock at the latest snapshot.
A28: Latest inventory value | B28: 37282642 | C28: Closing units × product cost at the latest snapshot.
A29: SKUs at/below reorder | B29: 64 | C29: Distinct latest-snapshot SKUs at or below product reorder level.
